{"word":"büktürtmek","pos":"verb","senses":[{"glosses":["To let somebody find somebody else bend something"]},{"glosses":["To let somebody find somebody else curve something"]},{"glosses":["To let somebody find somebody else entwist something"]},{"glosses":["To let somebody find somebody else fold something"]},{"glosses":["To let somebody find somebody else inflect something"]}],"etymology":"Intrusive form of büktürmek.","forms":[{"form":"büktürtür","tags":["present","singular","third-person"]},{"form":"no-table-tags","tags":["table-tags"]},{"form":"tr-conj","tags":["inflection-template"]},{"form":"büktürtürüm","tags":["aorist","singular","third-person"]},{"form":"büktürtürsün","tags":["aorist","first-person","plural"]},{"form":"büktürtür","tags":["aorist","plural","second-person"]},{"form":"büktürtürüz","tags":["aorist","plural","third-person"]},{"form":"büktürtürsünüz","tags":["aorist"]},{"form":"büktürtürler","tags":["aorist"]},{"form":"büktürtürmüşüm","tags":["aorist","inferential"]},{"form":"büktürtürmüşsün","tags":["aorist","second-person","singular"]},{"form":"büktürtürmüş","tags":["aorist","singular","third-person"]},{"form":"büktürtürmüşüz","tags":["aorist","first-person","plural"]},{"form":"büktürtürmüşsünüz","tags":["aorist","plural","second-person"]},{"form":"büktürtürlermiş","tags":["aorist","plural","third-person"]},{"form":"büktürtürdüm","tags":["aorist","past"]},{"form":"büktürtürdün","tags":["aorist","second-person","singular"]},{"form":"büktürtürdü","tags":["aorist","singular","third-person"]},{"form":"büktürtürdük","tags":["aorist","first-person","plural"]},{"form":"büktürtürdünüz","tags":["aorist","plural","second-person"]},{"form":"büktürtürlerdi","tags":["aorist","plural","third-person"]},{"form":"büktürtürsem","tags":["aorist","conditional"]},{"form":"büktürtürsen","tags":["aorist","second-person","singular"]},{"form":"büktürtürse","tags":["aorist","singular","third-person"]},{"form":"büktürtürsek","tags":["aorist","first-person","plural"]},{"form":"büktürtürseniz","tags":["aorist","plural","second-person"]},{"form":"büktürtürlerse","tags":["aorist","plural","third-person"]},{"form":"büktürtüyorum","tags":["continuative","singular","third-person"]},{"form":"büktürtüyorsun","tags":["continuative","first-person","plural"]},{"form":"büktürtüyor","tags":["continuative","plural","second-person"]},{"form":"büktürtüyoruz","tags":["continuative","plural","third-person"]},{"form":"büktürtüyorsunuz","tags":["continuative"]},{"form":"büktürtüyorlar","tags":["continuative"]},{"form":"büktürtüyormuşum","tags":["continuative","inferential"]},{"form":"büktürtüyormuşsun","tags":["continuative","second-person","singular"]},{"form":"büktürtüyormuş","tags":["continuative","singular","third-person"]},{"form":"büktürtüyormuşuz","tags":["continuative","first-person","plural"]},{"form":"büktürtüyormuşsunuz","tags":["continuative","plural","second-person"]},{"form":"büktürtüyorlarmış","tags":["continuative","plural","third-person"]},{"form":"büktürtüyordum","tags":["continuative","past"]},{"form":"büktürtüyordun","tags":["continuative","second-person","singular"]},{"form":"büktürtüyordu","tags":["continuative","singular","third-person"]},{"form":"büktürtüyorduk","tags":["continuative","first-person","plural"]},{"form":"büktürtüyordunuz","tags":["continuative","plural","second-person"]},{"form":"büktürtüyorlardı","tags":["continuative","plural","third-person"]},{"form":"büktürtüyorsam","tags":["conditional","continuative"]},{"form":"büktürtüyorsan","tags":["continuative","second-person","singular"]},{"form":"büktürtüyorsa","tags":["continuative","singular","third-person"]},{"form":"büktürtüyorsak","tags":["continuative","first-person","plural"]},{"form":"büktürtüyorsanız","tags":["continuative","plural","second-person"]},{"form":"büktürtüyorlarsa","tags":["continuative","plural","third-person"]},{"form":"büktürtmüşüm","tags":["inferential","singular","third-person"]},{"form":"büktürtmüşsün","tags":["first-person","inferential","plural"]},{"form":"büktürtmüş","tags":["inferential","plural","second-person"]},{"form":"büktürtmüşüz","tags":["inferential","plural","third-person"]},{"form":"büktürtmüşsünüz","tags":["inferential"]},{"form":"büktürtmüşler","tags":["inferential"]},{"form":"büktürtmüşmüşüm","tags":["inferential"]},{"form":"büktürtmüşmüşsün","tags":["inferential","second-person","singular"]},{"form":"büktürtmüşmüş","tags":["inferential","singular","third-person"]},{"form":"büktürtmüşmüşüz","tags":["first-person","inferential","plural"]},{"form":"büktürtmüşmüşsünüz","tags":["inferential","plural","second-person"]},{"form":"büktürtmüşlermiş","tags":["inferential","plural","third-person"]},{"form":"büktürtmüştüm","tags":["inferential","past"]},{"form":"büktürtmüştün","tags":["inferential","second-person","singular"]},{"form":"büktürtmüştü","tags":["inferential","singular","third-person"]},{"form":"büktürtmüştük","tags":["first-person","inferential","plural"]},{"form":"büktürtmüştünüz","tags":["inferential","plural","second-person"]},{"form":"büktürtmüşlerdi","tags":["inferential","plural","third-person"]},{"form":"büktürtmüşsem","tags":["conditional"]},{"form":"büktürtmüşsen","tags":["inferential","second-person","singular"]},{"form":"büktürtmüşse","tags":["inferential","singular","third-person"]},{"form":"büktürtmüşsek","tags":["first-person","inferential","plural"]},{"form":"büktürtmüşseniz","tags":["inferential","plural","second-person"]},{"form":"büktürtmüşlerse","tags":["inferential","plural","third-person"]},{"form":"büktürteceğim","tags":["future","singular","third-person"]},{"form":"büktürteceksin","tags":["first-person","future","plural"]},{"form":"büktürtecek","tags":["future","plural","second-person"]},{"form":"büktürteceğiz","tags":["future","plural","third-person"]},{"form":"büktürteceksiniz","tags":["future"]},{"form":"büktürtecekler","tags":["future"]},{"form":"büktürtecekmişim","tags":["future","inferential"]},{"form":"büktürtecekmişsin","tags":["future","second-person","singular"]},{"form":"büktürtecekmiş","tags":["future","singular","third-person"]},{"form":"büktürtecekmişiz","tags":["first-person","future","plural"]},{"form":"büktürtecekmişsiniz","tags":["future","plural","second-person"]},{"form":"büktürteceklermiş","tags":["future","plural","third-person"]},{"form":"büktürtecektim","tags":["future","past"]},{"form":"büktürtecektin","tags":["future","second-person","singular"]},{"form":"büktürtecekti","tags":["future","singular","third-person"]},{"form":"büktürtecektik","tags":["first-person","future","plural"]},{"form":"büktürtecektiniz","tags":["future","plural","second-person"]},{"form":"büktürteceklerdi","tags":["future","plural","third-person"]},{"form":"büktürteceksem","tags":["conditional","future"]},{"form":"büktürteceksen","tags":["future","second-person","singular"]},{"form":"büktürtecekse","tags":["future","singular","third-person"]},{"form":"büktürteceksek","tags":["first-person","future","plural"]},{"form":"büktürtecekseniz","tags":["future","plural","second-person"]},{"form":"büktürteceklerse","tags":["future","plural","third-person"]},{"form":"büktürtmekteyim","tags":["progressive","singular","third-person"]},{"form":"büktürtmektesin","tags":["first-person","plural","progressive"]},{"form":"büktürtmekte","tags":["plural","progressive","second-person"]},{"form":"büktürtmekteyiz","tags":["plural","progressive","third-person"]},{"form":"büktürtmektesiniz","tags":["progressive"]},{"form":"büktürtmekteler","tags":["progressive"]},{"form":"büktürtmekteymişim","tags":["inferential","progressive"]},{"form":"büktürtmekteymişsin","tags":["progressive","second-person","singular"]},{"form":"büktürtmekteymiş","tags":["progressive","singular","third-person"]},{"form":"büktürtmekteymişiz","tags":["first-person","plural","progressive"]},{"form":"büktürtmekteymişsiniz","tags":["plural","progressive","second-person"]},{"form":"büktürtmektelermiş","tags":["plural","progressive","third-person"]},{"form":"büktürtmekteydim","tags":["past","progressive"]},{"form":"büktürtmekteydin","tags":["progressive","second-person","singular"]},{"form":"büktürtmekteydi","tags":["progressive","singular","third-person"]},{"form":"büktürtmekteydik","tags":["first-person","plural","progressive"]},{"form":"büktürtmekteydiniz","tags":["plural","progressive","second-person"]},{"form":"büktürtmektelerdi","tags":["plural","progressive","third-person"]},{"form":"büktürtmekteysem","tags":["conditional","progressive"]},{"form":"büktürtmekteysen","tags":["progressive","second-person","singular"]},{"form":"büktürtmekteyse","tags":["progressive","singular","third-person"]},{"form":"büktürtmekteysek","tags":["first-person","plural","progressive"]},{"form":"büktürtmekteyseniz","tags":["plural","progressive","second-person"]},{"form":"büktürtmektelerse","tags":["plural","progressive","third-person"]},{"form":"büktürtmeliyim","tags":["necessitative","singular","third-person"]},{"form":"büktürtmelisin","tags":["first-person","necessitative","plural"]},{"form":"büktürtmeli","tags":["necessitative","plural","second-person"]},{"form":"büktürtmeliyiz","tags":["necessitative","plural","third-person"]},{"form":"büktürtmelisiniz","tags":["necessitative"]},{"form":"büktürtmeliler","tags":["necessitative"]},{"form":"büktürtmeliymişim","tags":["inferential"]},{"form":"büktürtmeliymişsin","tags":["necessitative","second-person","singular"]},{"form":"büktürtmeliymiş","tags":["necessitative","singular","third-person"]},{"form":"büktürtmeliymişiz","tags":["first-person","necessitative","plural"]},{"form":"büktürtmeliymişsiniz","tags":["necessitative","plural","second-person"]},{"form":"büktürtmelilermiş","tags":["necessitative","plural","third-person"]},{"form":"büktürtmeliydim","tags":["necessitative","past"]},{"form":"büktürtmeliydin","tags":["necessitative","second-person","singular"]},{"form":"büktürtmeliydi","tags":["necessitative","singular","third-person"]},{"form":"büktürtmeliydik","tags":["first-person","necessitative","plural"]},{"form":"büktürtmeliydiniz","tags":["necessitative","plural","second-person"]},{"form":"büktürtmelilerdi","tags":["necessitative","plural","third-person"]},{"form":"büktürtmeliysem","tags":["conditional"]},{"form":"büktürtmeliysen","tags":["necessitative","second-person","singular"]},{"form":"büktürtmeliyse","tags":["necessitative","singular","third-person"]},{"form":"büktürtmeliysek","tags":["first-person","necessitative","plural"]},{"form":"büktürtmeliyseniz","tags":["necessitative","plural","second-person"]},{"form":"büktürtmelilerse","tags":["necessitative","plural","third-person"]},{"form":"büktürttüm","tags":["past","singular","third-person"]},{"form":"büktürttün","tags":["first-person","past","plural"]},{"form":"büktürttü","tags":["past","plural","second-person"]},{"form":"büktürttük","tags":["past","plural","third-person"]},{"form":"büktürttünüz","tags":["past"]},{"form":"büktürttüler","tags":["past"]},{"form":"büktürttüysem","tags":["conditional","past"]},{"form":"büktürttüysen","tags":["past","second-person","singular"]},{"form":"büktürttüyse","tags":["past","singular","third-person"]},{"form":"büktürttüysek","tags":["first-person","past","plural"]},{"form":"büktürttüyseniz","tags":["past","plural","second-person"]},{"form":"büktürttülerse","tags":["past","plural","third-person"]},{"form":"büktürtsem","tags":["conditional","singular","third-person"]},{"form":"büktürtsen","tags":["conditional","first-person","plural"]},{"form":"büktürtse","tags":["conditional","plural","second-person"]},{"form":"büktürtsek","tags":["conditional","plural","third-person"]},{"form":"büktürtseniz","tags":["conditional"]},{"form":"büktürtseler","tags":["conditional"]},{"form":"büktürtseymişim","tags":["inferential"]},{"form":"büktürtseymişsin","tags":["conditional","second-person","singular"]},{"form":"büktürtseymiş","tags":["conditional","singular","third-person"]},{"form":"büktürtseymişiz","tags":["conditional","first-person","plural"]},{"form":"büktürtseymişsiniz","tags":["conditional","plural","second-person"]},{"form":"büktürtselermiş","tags":["conditional","plural","third-person"]},{"form":"büktürtseydim","tags":["conditional","past"]},{"form":"büktürtseydin","tags":["conditional","second-person","singular"]},{"form":"büktürtseydi","tags":["conditional","singular","third-person"]},{"form":"büktürtseydik","tags":["conditional","first-person","plural"]},{"form":"büktürtseydiniz","tags":["conditional","plural","second-person"]},{"form":"büktürtselerdi","tags":["conditional","plural","third-person"]},{"form":"büktürteyim","tags":["conditional","optative","singular"]},{"form":"büktürtesin","tags":["optative","second-person","singular"]},{"form":"büktürte","tags":["optative","singular","third-person"]},{"form":"büktürtelim","tags":["first-person","optative","plural"]},{"form":"büktürtesiniz","tags":["optative","plural","second-person"]},{"form":"büktürteler","tags":["optative","plural","third-person"]},{"form":"-","tags":["imperative","singular","third-person"]},{"form":"büktürt","tags":["first-person","imperative","plural"]},{"form":"büktürtsün","tags":["imperative","plural","second-person"]},{"form":"-","tags":["imperative","plural","third-person"]},{"form":"büktürtün","tags":["imperative"]},{"form":"büktürtsünler","tags":["imperative"]},{"form":"büktürtünüz","tags":["imperative","second-person","singular"]},{"form":"-","tags":["first-person","imperative","plural"]},{"form":"büktürtünüz","tags":["imperative","plural","second-person"]},{"form":"büktürtsene","tags":["imperative","second-person","singular"]},{"form":"büktürtsenize","tags":["imperative","plural","second-person"]},{"form":"büktürtmek","tags":["imperative","infinitive"]},{"form":"büktürtme","tags":["imperative","noun-from-verb"]},{"form":"büktürten","tags":["imperative","imperfective","impersonal","participle"]},{"form":"büktürtmüş","tags":["imperative","impersonal","participle","perfective"]},{"form":"büktürtecek","tags":["imperative","impersonal","participle","prospective"]},{"form":"büktürttüğüm","tags":["imperative","non-prospective","participle","personal","singular"]},{"form":"büktürttüğün","tags":["non-prospective","participle","second-person","singular"]},{"form":"büktürttüğü","tags":["non-prospective","participle","singular","third-person"]},{"form":"büktürttüğümüz","tags":["first-person","non-prospective","participle","plural"]},{"form":"büktürttüğünüz","tags":["non-prospective","participle","plural","second-person"]},{"form":"büktürttükleri","tags":["non-prospective","participle","plural","third-person"]},{"form":"büktürteceğim","tags":["imperative","participle","personal","prospective","singular"]},{"form":"büktürteceğin","tags":["participle","prospective","second-person","singular"]},{"form":"büktürteceği","tags":["participle","prospective","singular","third-person"]},{"form":"büktürteceğimiz","tags":["first-person","participle","plural","prospective"]},{"form":"büktürteceğiniz","tags":["participle","plural","prospective","second-person"]},{"form":"büktürtecekleri","tags":["participle","plural","prospective","third-person"]},{"form":"büktürtürken","tags":["error-unrecognized-form","plural"]},{"form":"büktürtünce","tags":["error-unrecognized-form","specific"]},{"form":"büktürtüp","tags":["error-unrecognized-form"]},{"form":"büktürteli","tags":["error-unrecognized-form"]},{"form":"büktürtesiye","tags":["error-unrecognized-form"]},{"form":"büktürttükçe","tags":["error-unrecognized-form"]},{"form":"büktürterek","tags":["error-unrecognized-form","plural"]},{"form":"büktürte büktürte","tags":["error-unrecognized-form"]},{"form":"büktürtürcesine","tags":["error-unrecognized-form"]},{"form":"negative","tags":["table-tags"]},{"form":"tr-conj","tags":["inflection-template"]},{"form":"büktürtmem","tags":["aorist","negative","singular","third-person"]},{"form":"büktürtmezsin","tags":["aorist","first-person","negative","plural"]},{"form":"büktürtmez","tags":["aorist","negative","plural","second-person"]},{"form":"büktürtmeyiz","tags":["aorist","negative","plural","third-person"]},{"form":"büktürtmezsiniz","tags":["aorist","negative"]},{"form":"büktürtmezler","tags":["aorist","negative"]},{"form":"büktürtmezmişim","tags":["aorist","inferential","negative"]},{"form":"büktürtmezmişsin","tags":["aorist","negative","second-person","singular"]},{"form":"büktürtmezmiş","tags":["aorist","negative","singular","third-person"]},{"form":"büktürtmezmişiz","tags":["aorist","first-person","negative","plural"]},{"form":"büktürtmezmişsiniz","tags":["aorist","negative","plural","second-person"]},{"form":"büktürtmezlermiş","tags":["aorist","negative","plural","third-person"]},{"form":"büktürtmezdim","tags":["aorist","negative","past"]},{"form":"büktürtmezdin","tags":["aorist","negative","second-person","singular"]},{"form":"büktürtmezdi","tags":["aorist","negative","singular","third-person"]},{"form":"büktürtmezdik","tags":["aorist","first-person","negative","plural"]},{"form":"büktürtmezdiniz","tags":["aorist","negative","plural","second-person"]},{"form":"büktürtmezlerdi","tags":["aorist","negative","plural","third-person"]},{"form":"büktürtmezsem","tags":["aorist","conditional","negative"]},{"form":"büktürtmezsen","tags":["aorist","negative","second-person","singular"]},{"form":"büktürtmezse","tags":["aorist","negative","singular","third-person"]},{"form":"büktürtmezsek","tags":["aorist","first-person","negative","plural"]},{"form":"büktürtmezseniz","tags":["aorist","negative","plural","second-person"]},{"form":"büktürtmezlerse","tags":["aorist","negative","plural","third-person"]},{"form":"büktürtmüyorum","tags":["continuative","negative","singular","third-person"]},{"form":"büktürtmüyorsun","tags":["continuative","first-person","negative","plural"]},{"form":"büktürtmüyor","tags":["continuative","negative","plural","second-person"]},{"form":"büktürtmüyoruz","tags":["continuative","negative","plural","third-person"]},{"form":"büktürtmüyorsunuz","tags":["continuative","negative"]},{"form":"büktürtmüyorlar","tags":["continuative","negative"]},{"form":"büktürtmüyormuşum","tags":["continuative","inferential","negative"]},{"form":"büktürtmüyormuşsun","tags":["continuative","negative","second-person","singular"]},{"form":"büktürtmüyormuş","tags":["continuative","negative","singular","third-person"]},{"form":"büktürtmüyormuşuz","tags":["continuative","first-person","negative","plural"]},{"form":"büktürtmüyormuşsunuz","tags":["continuative","negative","plural","second-person"]},{"form":"büktürtmüyorlarmış","tags":["continuative","negative","plural","third-person"]},{"form":"büktürtmüyordum","tags":["continuative","negative","past"]},{"form":"büktürtmüyordun","tags":["continuative","negative","second-person","singular"]},{"form":"büktürtmüyordu","tags":["continuative","negative","singular","third-person"]},{"form":"büktürtmüyorduk","tags":["continuative","first-person","negative","plural"]},{"form":"büktürtmüyordunuz","tags":["continuative","negative","plural","second-person"]},{"form":"büktürtmüyorlardı","tags":["continuative","negative","plural","third-person"]},{"form":"büktürtmüyorsam","tags":["conditional","continuative","negative"]},{"form":"büktürtmüyorsan","tags":["continuative","negative","second-person","singular"]},{"form":"büktürtmüyorsa","tags":["continuative","negative","singular","third-person"]},{"form":"büktürtmüyorsak","tags":["continuative","first-person","negative","plural"]},{"form":"büktürtmüyorsanız","tags":["continuative","negative","plural","second-person"]},{"form":"büktürtmüyorlarsa","tags":["continuative","negative","plural","third-person"]},{"form":"büktürtmemişim","tags":["inferential","negative","singular","third-person"]},{"form":"büktürtmemişsin","tags":["first-person","inferential","negative","plural"]},{"form":"büktürtmemiş","tags":["inferential","negative","plural","second-person"]},{"form":"büktürtmemişiz","tags":["inferential","negative","plural","third-person"]},{"form":"büktürtmemişsiniz","tags":["inferential","negative"]},{"form":"büktürtmemişler","tags":["inferential","negative"]},{"form":"büktürtmemişmişim","tags":["inferential","negative"]},{"form":"büktürtmemişmişsin","tags":["inferential","negative","second-person","singular"]},{"form":"büktürtmemişmiş","tags":["inferential","negative","singular","third-person"]},{"form":"büktürtmemişmişiz","tags":["first-person","inferential","negative","plural"]},{"form":"büktürtmemişmişsiniz","tags":["inferential","negative","plural","second-person"]},{"form":"büktürtmemişlermiş","tags":["inferential","negative","plural","third-person"]},{"form":"büktürtmemiştim","tags":["inferential","negative","past"]},{"form":"büktürtmemiştin","tags":["inferential","negative","second-person","singular"]},{"form":"büktürtmemişti","tags":["inferential","negative","singular","third-person"]},{"form":"büktürtmemiştik","tags":["first-person","inferential","negative","plural"]},{"form":"büktürtmemiştiniz","tags":["inferential","negative","plural","second-person"]},{"form":"büktürtmemişlerdi","tags":["inferential","negative","plural","third-person"]},{"form":"büktürtmemişsem","tags":["conditional","negative"]},{"form":"büktürtmemişsen","tags":["inferential","negative","second-person","singular"]},{"form":"büktürtmemişse","tags":["inferential","negative","singular","third-person"]},{"form":"büktürtmemişsek","tags":["first-person","inferential","negative","plural"]},{"form":"büktürtmemişseniz","tags":["inferential","negative","plural","second-person"]},{"form":"büktürtmemişlerse","tags":["inferential","negative","plural","third-person"]},{"form":"büktürtmeyeceğim","tags":["future","negative","singular","third-person"]},{"form":"büktürtmeyeceksin","tags":["first-person","future","negative","plural"]},{"form":"büktürtmeyecek","tags":["future","negative","plural","second-person"]},{"form":"büktürtmeyeceğiz","tags":["future","negative","plural","third-person"]},{"form":"büktürtmeyeceksiniz","tags":["future","negative"]},{"form":"büktürtmeyecekler","tags":["future","negative"]},{"form":"büktürtmeyecekmişim","tags":["future","inferential","negative"]},{"form":"büktürtmeyecekmişsin","tags":["future","negative","second-person","singular"]},{"form":"büktürtmeyecekmiş","tags":["future","negative","singular","third-person"]},{"form":"büktürtmeyecekmişiz","tags":["first-person","future","negative","plural"]},{"form":"büktürtmeyecekmişsiniz","tags":["future","negative","plural","second-person"]},{"form":"büktürtmeyeceklermiş","tags":["future","negative","plural","third-person"]},{"form":"büktürtmeyecektim","tags":["future","negative","past"]},{"form":"büktürtmeyecektin","tags":["future","negative","second-person","singular"]},{"form":"büktürtmeyecekti","tags":["future","negative","singular","third-person"]},{"form":"büktürtmeyecektik","tags":["first-person","future","negative","plural"]},{"form":"büktürtmeyecektiniz","tags":["future","negative","plural","second-person"]},{"form":"büktürtmeyeceklerdi","tags":["future","negative","plural","third-person"]},{"form":"büktürtmeyeceksem","tags":["conditional","future","negative"]},{"form":"büktürtmeyeceksen","tags":["future","negative","second-person","singular"]},{"form":"büktürtmeyecekse","tags":["future","negative","singular","third-person"]},{"form":"büktürtmeyeceksek","tags":["first-person","future","negative","plural"]},{"form":"büktürtmeyecekseniz","tags":["future","negative","plural","second-person"]},{"form":"büktürtmeyeceklerse","tags":["future","negative","plural","third-person"]},{"form":"büktürtmemekteyim","tags":["negative","progressive","singular","third-person"]},{"form":"büktürtmemektesin","tags":["first-person","negative","plural","progressive"]},{"form":"büktürtmemekte","tags":["negative","plural","progressive","second-person"]},{"form":"büktürtmemekteyiz","tags":["negative","plural","progressive","third-person"]},{"form":"büktürtmemektesiniz","tags":["negative","progressive"]},{"form":"büktürtmemekteler","tags":["negative","progressive"]},{"form":"büktürtmemekteymişim","tags":["inferential","negative","progressive"]},{"form":"büktürtmemekteymişsin","tags":["negative","progressive","second-person","singular"]},{"form":"büktürtmemekteymiş","tags":["negative","progressive","singular","third-person"]},{"form":"büktürtmemekteymişiz","tags":["first-person","negative","plural","progressive"]},{"form":"büktürtmemekteymişsiniz","tags":["negative","plural","progressive","second-person"]},{"form":"büktürtmemektelermiş","tags":["negative","plural","progressive","third-person"]},{"form":"büktürtmemekteydim","tags":["negative","past","progressive"]},{"form":"büktürtmemekteydin","tags":["negative","progressive","second-person","singular"]},{"form":"büktürtmemekteydi","tags":["negative","progressive","singular","third-person"]},{"form":"büktürtmemekteydik","tags":["first-person","negative","plural","progressive"]},{"form":"büktürtmemekteydiniz","tags":["negative","plural","progressive","second-person"]},{"form":"büktürtmemektelerdi","tags":["negative","plural","progressive","third-person"]},{"form":"büktürtmemekteysem","tags":["conditional","negative","progressive"]},{"form":"büktürtmemekteysen","tags":["negative","progressive","second-person","singular"]},{"form":"büktürtmemekteyse","tags":["negative","progressive","singular","third-person"]},{"form":"büktürtmemekteysek","tags":["first-person","negative","plural","progressive"]},{"form":"büktürtmemekteyseniz","tags":["negative","plural","progressive","second-person"]},{"form":"büktürtmemektelerse","tags":["negative","plural","progressive","third-person"]},{"form":"büktürtmemeliyim","tags":["necessitative","negative","singular","third-person"]},{"form":"büktürtmemelisin","tags":["first-person","necessitative","negative","plural"]},{"form":"büktürtmemeli","tags":["necessitative","negative","plural","second-person"]},{"form":"büktürtmemeliyiz","tags":["necessitative","negative","plural","third-person"]},{"form":"büktürtmemelisiniz","tags":["necessitative","negative"]},{"form":"büktürtmemeliler","tags":["necessitative","negative"]},{"form":"büktürtmemeliymişim","tags":["inferential","negative"]},{"form":"büktürtmemeliymişsin","tags":["necessitative","negative","second-person","singular"]},{"form":"büktürtmemeliymiş","tags":["necessitative","negative","singular","third-person"]},{"form":"büktürtmemeliymişiz","tags":["first-person","necessitative","negative","plural"]},{"form":"büktürtmemeliymişsiniz","tags":["necessitative","negative","plural","second-person"]},{"form":"büktürtmemelilermiş","tags":["necessitative","negative","plural","third-person"]},{"form":"büktürtmemeliydim","tags":["necessitative","negative","past"]},{"form":"büktürtmemeliydin","tags":["necessitative","negative","second-person","singular"]},{"form":"büktürtmemeliydi","tags":["necessitative","negative","singular","third-person"]},{"form":"büktürtmemeliydik","tags":["first-person","necessitative","negative","plural"]},{"form":"büktürtmemeliydiniz","tags":["necessitative","negative","plural","second-person"]},{"form":"büktürtmemelilerdi","tags":["necessitative","negative","plural","third-person"]},{"form":"büktürtmemeliysem","tags":["conditional","negative"]},{"form":"büktürtmemeliysen","tags":["necessitative","negative","second-person","singular"]},{"form":"büktürtmemeliyse","tags":["necessitative","negative","singular","third-person"]},{"form":"büktürtmemeliysek","tags":["first-person","necessitative","negative","plural"]},{"form":"büktürtmemeliyseniz","tags":["necessitative","negative","plural","second-person"]},{"form":"büktürtmemelilerse","tags":["necessitative","negative","plural","third-person"]},{"form":"büktürtmedim","tags":["negative","past","singular","third-person"]},{"form":"büktürtmedin","tags":["first-person","negative","past","plural"]},{"form":"büktürtmedi","tags":["negative","past","plural","second-person"]},{"form":"büktürtmedik","tags":["negative","past","plural","third-person"]},{"form":"büktürtmediniz","tags":["negative","past"]},{"form":"büktürtmediler","tags":["negative","past"]},{"form":"büktürtmediysem","tags":["conditional","negative","past"]},{"form":"büktürtmediysen","tags":["negative","past","second-person","singular"]},{"form":"büktürtmediyse","tags":["negative","past","singular","third-person"]},{"form":"büktürtmediysek","tags":["first-person","negative","past","plural"]},{"form":"büktürtmediyseniz","tags":["negative","past","plural","second-person"]},{"form":"büktürtmedilerse","tags":["negative","past","plural","third-person"]},{"form":"büktürtmesem","tags":["conditional","negative","singular","third-person"]},{"form":"büktürtmesen","tags":["conditional","first-person","negative","plural"]},{"form":"büktürtmese","tags":["conditional","negative","plural","second-person"]},{"form":"büktürtmesek","tags":["conditional","negative","plural","third-person"]},{"form":"büktürtmeseniz","tags":["conditional","negative"]},{"form":"büktürtmeseler","tags":["conditional","negative"]},{"form":"büktürtmeseymişim","tags":["inferential","negative"]},{"form":"büktürtmeseymişsin","tags":["conditional","negative","second-person","singular"]},{"form":"büktürtmeseymiş","tags":["conditional","negative","singular","third-person"]},{"form":"büktürtmeseymişiz","tags":["conditional","first-person","negative","plural"]},{"form":"büktürtmeseymişsiniz","tags":["conditional","negative","plural","second-person"]},{"form":"büktürtmeselermiş","tags":["conditional","negative","plural","third-person"]},{"form":"büktürtmeseydim","tags":["conditional","negative","past"]},{"form":"büktürtmeseydin","tags":["conditional","negative","second-person","singular"]},{"form":"büktürtmeseydi","tags":["conditional","negative","singular","third-person"]},{"form":"büktürtmeseydik","tags":["conditional","first-person","negative","plural"]},{"form":"büktürtmeseydiniz","tags":["conditional","negative","plural","second-person"]},{"form":"büktürtmeselerdi","tags":["conditional","negative","plural","third-person"]},{"form":"büktürtmeyeyim","tags":["conditional","negative","optative","singular"]},{"form":"büktürtmeyesin","tags":["negative","optative","second-person","singular"]},{"form":"büktürtmeye","tags":["negative","optative","singular","third-person"]},{"form":"büktürtmeyelim","tags":["first-person","negative","optative","plural"]},{"form":"büktürtmeyesiniz","tags":["negative","optative","plural","second-person"]},{"form":"büktürtmeyeler","tags":["negative","optative","plural","third-person"]},{"form":"-","tags":["imperative","negative","singular","third-person"]},{"form":"büktürtme","tags":["first-person","imperative","negative","plural"]},{"form":"büktürtmesin","tags":["imperative","negative","plural","second-person"]},{"form":"-","tags":["imperative","negative","plural","third-person"]},{"form":"büktürtmeyin","tags":["imperative","negative"]},{"form":"büktürtmesinler","tags":["imperative","negative"]},{"form":"büktürtmeyiniz","tags":["imperative","negative","second-person","singular"]},{"form":"-","tags":["first-person","imperative","negative","plural"]},{"form":"büktürtmeyiniz","tags":["imperative","negative","plural","second-person"]},{"form":"büktürtmesene","tags":["imperative","negative","second-person","singular"]},{"form":"büktürtmesenize","tags":["imperative","negative","plural","second-person"]},{"form":"büktürtmemek","tags":["imperative","infinitive","negative"]},{"form":"büktürtmeme","tags":["imperative","negative","noun-from-verb"]},{"form":"büktürtmeyen","tags":["imperative","imperfective","impersonal","negative","participle"]},{"form":"büktürtmemiş","tags":["imperative","impersonal","negative","participle","perfective"]},{"form":"büktürtmeyecek","tags":["imperative","impersonal","negative","participle","prospective"]},{"form":"büktürtmediğim","tags":["imperative","negative","non-prospective","participle","personal","singular"]},{"form":"büktürtmediğin","tags":["negative","non-prospective","participle","second-person","singular"]},{"form":"büktürtmediği","tags":["negative","non-prospective","participle","singular","third-person"]},{"form":"büktürtmediğimiz","tags":["first-person","negative","non-prospective","participle","plural"]},{"form":"büktürtmediğiniz","tags":["negative","non-prospective","participle","plural","second-person"]},{"form":"büktürtmedikleri","tags":["negative","non-prospective","participle","plural","third-person"]},{"form":"büktürtmeyeceğim","tags":["imperative","negative","participle","personal","prospective","singular"]},{"form":"büktürtmeyeceğin","tags":["negative","participle","prospective","second-person","singular"]},{"form":"büktürtmeyeceği","tags":["negative","participle","prospective","singular","third-person"]},{"form":"büktürtmeyeceğimiz","tags":["first-person","negative","participle","plural","prospective"]},{"form":"büktürtmeyeceğiniz","tags":["negative","participle","plural","prospective","second-person"]},{"form":"büktürtmeyecekleri","tags":["negative","participle","plural","prospective","third-person"]},{"form":"büktürtmezken","tags":["error-unrecognized-form","negative","plural"]},{"form":"büktürtmeyince","tags":["error-unrecognized-form","negative","specific"]},{"form":"büktürtmeyip","tags":["error-unrecognized-form","negative"]},{"form":"büktürtmeyeli","tags":["error-unrecognized-form","negative"]},{"form":"büktürtmeyesiye","tags":["error-unrecognized-form","negative"]},{"form":"büktürtmedikçe","tags":["error-unrecognized-form","negative"]},{"form":"büktürtmeyerek","tags":["error-unrecognized-form","negative","plural"]},{"form":"büktürtmeye büktürtmeye","tags":["error-unrecognized-form","negative"]},{"form":"büktürtmezcesine","tags":["error-unrecognized-form","negative"]},{"form":"no-table-tags","tags":["table-tags"]},{"form":"tr-conj","tags":["inflection-template"]},{"form":"büktürtebilirim","tags":["aorist","singular","third-person"]},{"form":"büktürtebilirsin","tags":["aorist","first-person","plural"]},{"form":"büktürtebilir","tags":["aorist","plural","second-person"]},{"form":"büktürtebiliriz","tags":["aorist","plural","third-person"]},{"form":"büktürtebilirsiniz","tags":["aorist"]},{"form":"büktürtebilirler","tags":["aorist"]},{"form":"büktürtebilirmişim","tags":["aorist","inferential"]},{"form":"büktürtebilirmişsin","tags":["aorist","second-person","singular"]},{"form":"büktürtebilirmiş","tags":["aorist","singular","third-person"]},{"form":"büktürtebilirmişiz","tags":["aorist","first-person","plural"]},{"form":"büktürtebilirmişsiniz","tags":["aorist","plural","second-person"]},{"form":"büktürtebilirlermiş","tags":["aorist","plural","third-person"]},{"form":"büktürtebilirdim","tags":["aorist","past"]},{"form":"büktürtebilirdin","tags":["aorist","second-person","singular"]},{"form":"büktürtebilirdi","tags":["aorist","singular","third-person"]},{"form":"büktürtebilirdik","tags":["aorist","first-person","plural"]},{"form":"büktürtebilirdiniz","tags":["aorist","plural","second-person"]},{"form":"büktürtebilirlerdi","tags":["aorist","plural","third-person"]},{"form":"büktürtebilirsem","tags":["aorist","conditional"]},{"form":"büktürtebilirsen","tags":["aorist","second-person","singular"]},{"form":"büktürtebilirse","tags":["aorist","singular","third-person"]},{"form":"büktürtebilirsek","tags":["aorist","first-person","plural"]},{"form":"büktürtebilirseniz","tags":["aorist","plural","second-person"]},{"form":"büktürtebilirlerse","tags":["aorist","plural","third-person"]},{"form":"büktürtebiliyorum","tags":["continuative","singular","third-person"]},{"form":"büktürtebiliyorsun","tags":["continuative","first-person","plural"]},{"form":"büktürtebiliyor","tags":["continuative","plural","second-person"]},{"form":"büktürtebiliyoruz","tags":["continuative","plural","third-person"]},{"form":"büktürtebiliyorsunuz","tags":["continuative"]},{"form":"büktürtebiliyorlar","tags":["continuative"]},{"form":"büktürtebiliyormuşum","tags":["continuative","inferential"]},{"form":"büktürtebiliyormuşsun","tags":["continuative","second-person","singular"]},{"form":"büktürtebiliyormuş","tags":["continuative","singular","third-person"]},{"form":"büktürtebiliyormuşuz","tags":["continuative","first-person","plural"]},{"form":"büktürtebiliyormuşsunuz","tags":["continuative","plural","second-person"]},{"form":"büktürtebiliyorlarmış","tags":["continuative","plural","third-person"]},{"form":"büktürtebiliyordum","tags":["continuative","past"]},{"form":"büktürtebiliyordun","tags":["continuative","second-person","singular"]},{"form":"büktürtebiliyordu","tags":["continuative","singular","third-person"]},{"form":"büktürtebiliyorduk","tags":["continuative","first-person","plural"]},{"form":"büktürtebiliyordunuz","tags":["continuative","plural","second-person"]},{"form":"büktürtebiliyorlardı","tags":["continuative","plural","third-person"]},{"form":"büktürtebiliyorsam","tags":["conditional","continuative"]},{"form":"büktürtebiliyorsan","tags":["continuative","second-person","singular"]},{"form":"büktürtebiliyorsa","tags":["continuative","singular","third-person"]},{"form":"büktürtebiliyorsak","tags":["continuative","first-person","plural"]},{"form":"büktürtebiliyorsanız","tags":["continuative","plural","second-person"]},{"form":"büktürtebiliyorlarsa","tags":["continuative","plural","third-person"]},{"form":"büktürtebilmişim","tags":["inferential","singular","third-person"]},{"form":"büktürtebilmişsin","tags":["first-person","inferential","plural"]},{"form":"büktürtebilmiş","tags":["inferential","plural","second-person"]},{"form":"büktürtebilmişiz","tags":["inferential","plural","third-person"]},{"form":"büktürtebilmişsiniz","tags":["inferential"]},{"form":"büktürtebilmişler","tags":["inferential"]},{"form":"büktürtebilmişmişim","tags":["inferential"]},{"form":"büktürtebilmişmişsin","tags":["inferential","second-person","singular"]},{"form":"büktürtebilmişmiş","tags":["inferential","singular","third-person"]},{"form":"büktürtebilmişmişiz","tags":["first-person","inferential","plural"]},{"form":"büktürtebilmişmişsiniz","tags":["inferential","plural","second-person"]},{"form":"büktürtebilmişlermiş","tags":["inferential","plural","third-person"]},{"form":"büktürtebilmiştim","tags":["inferential","past"]},{"form":"büktürtebilmiştin","tags":["inferential","second-person","singular"]},{"form":"büktürtebilmişti","tags":["inferential","singular","third-person"]},{"form":"büktürtebilmiştik","tags":["first-person","inferential","plural"]},{"form":"büktürtebilmiştiniz","tags":["inferential","plural","second-person"]},{"form":"büktürtebilmişlerdi","tags":["inferential","plural","third-person"]},{"form":"büktürtebilmişsem","tags":["conditional"]},{"form":"büktürtebilmişsen","tags":["inferential","second-person","singular"]},{"form":"büktürtebilmişse","tags":["inferential","singular","third-person"]},{"form":"büktürtebilmişsek","tags":["first-person","inferential","plural"]},{"form":"büktürtebilmişseniz","tags":["inferential","plural","second-person"]},{"form":"büktürtebilmişlerse","tags":["inferential","plural","third-person"]},{"form":"büktürtebileceğim","tags":["future","singular","third-person"]},{"form":"büktürtebileceksin","tags":["first-person","future","plural"]},{"form":"büktürtebilecek","tags":["future","plural","second-person"]},{"form":"büktürtebileceğiz","tags":["future","plural","third-person"]},{"form":"büktürtebileceksiniz","tags":["future"]},{"form":"büktürtebilecekler","tags":["future"]},{"form":"büktürtebilecekmişim","tags":["future","inferential"]},{"form":"büktürtebilecekmişsin","tags":["future","second-person","singular"]},{"form":"büktürtebilecekmiş","tags":["future","singular","third-person"]},{"form":"büktürtebilecekmişiz","tags":["first-person","future","plural"]},{"form":"büktürtebilecekmişsiniz","tags":["future","plural","second-person"]},{"form":"büktürtebileceklermiş","tags":["future","plural","third-person"]},{"form":"büktürtebilecektim","tags":["future","past"]},{"form":"büktürtebilecektin","tags":["future","second-person","singular"]},{"form":"büktürtebilecekti","tags":["future","singular","third-person"]},{"form":"büktürtebilecektik","tags":["first-person","future","plural"]},{"form":"büktürtebilecektiniz","tags":["future","plural","second-person"]},{"form":"büktürtebileceklerdi","tags":["future","plural","third-person"]},{"form":"büktürtebileceksem","tags":["conditional","future"]},{"form":"büktürtebileceksen","tags":["future","second-person","singular"]},{"form":"büktürtebilecekse","tags":["future","singular","third-person"]},{"form":"büktürtebileceksek","tags":["first-person","future","plural"]},{"form":"büktürtebilecekseniz","tags":["future","plural","second-person"]},{"form":"büktürtebileceklerse","tags":["future","plural","third-person"]},{"form":"büktürtebilmekteyim","tags":["progressive","singular","third-person"]},{"form":"büktürtebilmektesin","tags":["first-person","plural","progressive"]},{"form":"büktürtebilmekte","tags":["plural","progressive","second-person"]},{"form":"büktürtebilmekteyiz","tags":["plural","progressive","third-person"]},{"form":"büktürtebilmektesiniz","tags":["progressive"]},{"form":"büktürtebilmekteler","tags":["progressive"]},{"form":"büktürtebilmekteymişim","tags":["inferential","progressive"]},{"form":"büktürtebilmekteymişsin","tags":["progressive","second-person","singular"]},{"form":"büktürtebilmekteymiş","tags":["progressive","singular","third-person"]},{"form":"büktürtebilmekteymişiz","tags":["first-person","plural","progressive"]},{"form":"büktürtebilmekteymişsiniz","tags":["plural","progressive","second-person"]},{"form":"büktürtebilmektelermiş","tags":["plural","progressive","third-person"]},{"form":"büktürtebilmekteydim","tags":["past","progressive"]},{"form":"büktürtebilmekteydin","tags":["progressive","second-person","singular"]},{"form":"büktürtebilmekteydi","tags":["progressive","singular","third-person"]},{"form":"büktürtebilmekteydik","tags":["first-person","plural","progressive"]},{"form":"büktürtebilmekteydiniz","tags":["plural","progressive","second-person"]},{"form":"büktürtebilmektelerdi","tags":["plural","progressive","third-person"]},{"form":"büktürtebilmekteysem","tags":["conditional","progressive"]},{"form":"büktürtebilmekteysen","tags":["progressive","second-person","singular"]},{"form":"büktürtebilmekteyse","tags":["progressive","singular","third-person"]},{"form":"büktürtebilmekteysek","tags":["first-person","plural","progressive"]},{"form":"büktürtebilmekteyseniz","tags":["plural","progressive","second-person"]},{"form":"büktürtebilmektelerse","tags":["plural","progressive","third-person"]},{"form":"büktürtebilmeliyim","tags":["necessitative","singular","third-person"]},{"form":"büktürtebilmelisin","tags":["first-person","necessitative","plural"]},{"form":"büktürtebilmeli","tags":["necessitative","plural","second-person"]},{"form":"büktürtebilmeliyiz","tags":["necessitative","plural","third-person"]},{"form":"büktürtebilmelisiniz","tags":["necessitative"]},{"form":"büktürtebilmeliler","tags":["necessitative"]},{"form":"büktürtebilmeliymişim","tags":["inferential"]},{"form":"büktürtebilmeliymişsin","tags":["necessitative","second-person","singular"]},{"form":"büktürtebilmeliymiş","tags":["necessitative","singular","third-person"]},{"form":"büktürtebilmeliymişiz","tags":["first-person","necessitative","plural"]},{"form":"büktürtebilmeliymişsiniz","tags":["necessitative","plural","second-person"]},{"form":"büktürtebilmelilermiş","tags":["necessitative","plural","third-person"]},{"form":"büktürtebilmeliydim","tags":["necessitative","past"]},{"form":"büktürtebilmeliydin","tags":["necessitative","second-person","singular"]},{"form":"büktürtebilmeliydi","tags":["necessitative","singular","third-person"]},{"form":"büktürtebilmeliydik","tags":["first-person","necessitative","plural"]},{"form":"büktürtebilmeliydiniz","tags":["necessitative","plural","second-person"]},{"form":"büktürtebilmelilerdi","tags":["necessitative","plural","third-person"]},{"form":"büktürtebilmeliysem","tags":["conditional"]},{"form":"büktürtebilmeliysen","tags":["necessitative","second-person","singular"]},{"form":"büktürtebilmeliyse","tags":["necessitative","singular","third-person"]},{"form":"büktürtebilmeliysek","tags":["first-person","necessitative","plural"]},{"form":"büktürtebilmeliyseniz","tags":["necessitative","plural","second-person"]},{"form":"büktürtebilmelilerse","tags":["necessitative","plural","third-person"]},{"form":"büktürtebildim","tags":["past","singular","third-person"]},{"form":"büktürtebildin","tags":["first-person","past","plural"]},{"form":"büktürtebildi","tags":["past","plural","second-person"]},{"form":"büktürtebildik","tags":["past","plural","third-person"]},{"form":"büktürtebildiniz","tags":["past"]},{"form":"büktürtebildiler","tags":["past"]},{"form":"büktürtebildiysem","tags":["conditional","past"]},{"form":"büktürtebildiysen","tags":["past","second-person","singular"]},{"form":"büktürtebildiyse","tags":["past","singular","third-person"]},{"form":"büktürtebildiysek","tags":["first-person","past","plural"]},{"form":"büktürtebildiyseniz","tags":["past","plural","second-person"]},{"form":"büktürtebildilerse","tags":["past","plural","third-person"]},{"form":"büktürtebilsem","tags":["conditional","singular","third-person"]},{"form":"büktürtebilsen","tags":["conditional","first-person","plural"]},{"form":"büktürtebilse","tags":["conditional","plural","second-person"]},{"form":"büktürtebilsek","tags":["conditional","plural","third-person"]},{"form":"büktürtebilseniz","tags":["conditional"]},{"form":"büktürtebilseler","tags":["conditional"]},{"form":"büktürtebilseymişim","tags":["conditional","past"]},{"form":"büktürtebilseymişsin","tags":["conditional","second-person","singular"]},{"form":"büktürtebilseymiş","tags":["conditional","singular","third-person"]},{"form":"büktürtebilseymişiz","tags":["conditional","first-person","plural"]},{"form":"büktürtebilseymişsiniz","tags":["conditional","plural","second-person"]},{"form":"büktürtebilselermiş","tags":["conditional","plural","third-person"]},{"form":"büktürtebilseydim","tags":["inferential"]},{"form":"büktürtebilseydin","tags":["conditional","second-person","singular"]},{"form":"büktürtebilseydi","tags":["conditional","singular","third-person"]},{"form":"büktürtebilseydik","tags":["conditional","first-person","plural"]},{"form":"büktürtebilseydiniz","tags":["conditional","plural","second-person"]},{"form":"büktürtebilselerdi","tags":["conditional","plural","third-person"]},{"form":"büktürtebileyim","tags":["conditional","optative","singular"]},{"form":"büktürtebilesin","tags":["optative","second-person","singular"]},{"form":"büktürtebile","tags":["optative","singular","third-person"]},{"form":"büktürtebilelim","tags":["first-person","optative","plural"]},{"form":"büktürtebilesiniz","tags":["optative","plural","second-person"]},{"form":"büktürtebileler","tags":["optative","plural","third-person"]},{"form":"-","tags":["imperative","singular","third-person"]},{"form":"büktürtebil","tags":["first-person","imperative","plural"]},{"form":"büktürtebilsin","tags":["imperative","plural","second-person"]},{"form":"-","tags":["imperative","plural","third-person"]},{"form":"büktürtebilin","tags":["imperative"]},{"form":"büktürtebilsinler","tags":["imperative"]},{"form":"büktürtebiliniz","tags":["imperative","second-person","singular"]},{"form":"-","tags":["first-person","imperative","plural"]},{"form":"büktürtebiliniz","tags":["imperative","plural","second-person"]},{"form":"büktürtebilsene","tags":["imperative","second-person","singular"]},{"form":"büktürtebilsenize","tags":["imperative","plural","second-person"]},{"form":"büktürtebilmek","tags":["imperative","infinitive"]},{"form":"büktürtebilme","tags":["imperative","noun-from-verb"]},{"form":"büktürtebilen","tags":["imperative","imperfective","impersonal","participle"]},{"form":"büktürtebilmiş","tags":["imperative","impersonal","participle","perfective"]},{"form":"büktürtebilecek","tags":["imperative","impersonal","participle","prospective"]},{"form":"büktürtebildiğim","tags":["imperative","non-prospective","participle","personal","singular"]},{"form":"büktürtebildiğin","tags":["non-prospective","participle","second-person","singular"]},{"form":"büktürtebildiği","tags":["non-prospective","participle","singular","third-person"]},{"form":"büktürtebildiğimiz","tags":["first-person","non-prospective","participle","plural"]},{"form":"büktürtebildiğiniz","tags":["non-prospective","participle","plural","second-person"]},{"form":"büktürtebildikleri","tags":["non-prospective","participle","plural","third-person"]},{"form":"büktürtebileceğim","tags":["imperative","participle","personal","prospective","singular"]},{"form":"büktürtebileceğin","tags":["participle","prospective","second-person","singular"]},{"form":"büktürtebileceği","tags":["participle","prospective","singular","third-person"]},{"form":"büktürtebileceğimiz","tags":["first-person","participle","plural","prospective"]},{"form":"büktürtebileceğiniz","tags":["participle","plural","prospective","second-person"]},{"form":"büktürtebilecekleri","tags":["participle","plural","prospective","third-person"]},{"form":"büktürtebilirken","tags":["error-unrecognized-form","plural"]},{"form":"büktürtebilince","tags":["error-unrecognized-form","specific"]},{"form":"büktürtebilip","tags":["error-unrecognized-form"]},{"form":"büktürtebileli","tags":["error-unrecognized-form"]},{"form":"büktürtebilesiye","tags":["error-unrecognized-form"]},{"form":"büktürtebildikçe","tags":["error-unrecognized-form"]},{"form":"büktürtebilerek","tags":["error-unrecognized-form","plural"]},{"form":"büktürtebile büktürtebile","tags":["error-unrecognized-form"]},{"form":"büktürtebilircesine","tags":["error-unrecognized-form"]},{"form":"no-table-tags","tags":["table-tags"]},{"form":"tr-conj","tags":["inflection-template"]},{"form":"büktürtemem","tags":["aorist","singular","third-person"]},{"form":"büktürtemezsin","tags":["aorist","first-person","plural"]},{"form":"büktürtemez","tags":["aorist","plural","second-person"]},{"form":"büktürtemeyiz","tags":["aorist","plural","third-person"]},{"form":"büktürtemezsiniz","tags":["aorist"]},{"form":"büktürtemezler","tags":["aorist"]},{"form":"büktürtemezmişim","tags":["aorist","inferential"]},{"form":"büktürtemezmişsin","tags":["aorist","second-person","singular"]},{"form":"büktürtemezmiş","tags":["aorist","singular","third-person"]},{"form":"büktürtemezmişiz","tags":["aorist","first-person","plural"]},{"form":"büktürtemezmişsiniz","tags":["aorist","plural","second-person"]},{"form":"büktürtemezlermiş","tags":["aorist","plural","third-person"]},{"form":"büktürtemezdim","tags":["aorist","past"]},{"form":"büktürtemezdin","tags":["aorist","second-person","singular"]},{"form":"büktürtemezdi","tags":["aorist","singular","third-person"]},{"form":"büktürtemezdik","tags":["aorist","first-person","plural"]},{"form":"büktürtemezdiniz","tags":["aorist","plural","second-person"]},{"form":"büktürtemezlerdi","tags":["aorist","plural","third-person"]},{"form":"büktürtemezsem","tags":["aorist","conditional"]},{"form":"büktürtemezsen","tags":["aorist","second-person","singular"]},{"form":"büktürtemezse","tags":["aorist","singular","third-person"]},{"form":"büktürtemezsek","tags":["aorist","first-person","plural"]},{"form":"büktürtemezseniz","tags":["aorist","plural","second-person"]},{"form":"büktürtemezlerse","tags":["aorist","plural","third-person"]},{"form":"büktürtemiyorum","tags":["continuative","singular","third-person"]},{"form":"büktürtemiyorsun","tags":["continuative","first-person","plural"]},{"form":"büktürtemiyor","tags":["continuative","plural","second-person"]},{"form":"büktürtemiyoruz","tags":["continuative","plural","third-person"]},{"form":"büktürtemiyorsunuz","tags":["continuative"]},{"form":"büktürtemiyorlar","tags":["continuative"]},{"form":"büktürtemiyormuşum","tags":["continuative","inferential"]},{"form":"büktürtemiyormuşsun","tags":["continuative","second-person","singular"]},{"form":"büktürtemiyormuş","tags":["continuative","singular","third-person"]},{"form":"büktürtemiyormuşuz","tags":["continuative","first-person","plural"]},{"form":"büktürtemiyormuşsunuz","tags":["continuative","plural","second-person"]},{"form":"büktürtemiyorlarmış","tags":["continuative","plural","third-person"]},{"form":"büktürtemiyordum","tags":["continuative","past"]},{"form":"büktürtemiyordun","tags":["continuative","second-person","singular"]},{"form":"büktürtemiyordu","tags":["continuative","singular","third-person"]},{"form":"büktürtemiyorduk","tags":["continuative","first-person","plural"]},{"form":"büktürtemiyordunuz","tags":["continuative","plural","second-person"]},{"form":"büktürtemiyorlardı","tags":["continuative","plural","third-person"]},{"form":"büktürtemiyorsam","tags":["conditional","continuative"]},{"form":"büktürtemiyorsan","tags":["continuative","second-person","singular"]},{"form":"büktürtemiyorsa","tags":["continuative","singular","third-person"]},{"form":"büktürtemiyorsak","tags":["continuative","first-person","plural"]},{"form":"büktürtemiyorsanız","tags":["continuative","plural","second-person"]},{"form":"büktürtemiyorlarsa","tags":["continuative","plural","third-person"]},{"form":"büktürtememişim","tags":["inferential","singular","third-person"]},{"form":"büktürtememişsin","tags":["first-person","inferential","plural"]},{"form":"büktürtememiş","tags":["inferential","plural","second-person"]},{"form":"büktürtememişiz","tags":["inferential","plural","third-person"]},{"form":"büktürtememişsiniz","tags":["inferential"]},{"form":"büktürtememişler","tags":["inferential"]},{"form":"büktürtememişmişim","tags":["inferential"]},{"form":"büktürtememişmişsin","tags":["inferential","second-person","singular"]},{"form":"büktürtememişmiş","tags":["inferential","singular","third-person"]},{"form":"büktürtememişmişiz","tags":["first-person","inferential","plural"]},{"form":"büktürtememişmişsiniz","tags":["inferential","plural","second-person"]},{"form":"büktürtememişlermiş","tags":["inferential","plural","third-person"]},{"form":"büktürtememiştim","tags":["inferential","past"]},{"form":"büktürtememiştin","tags":["inferential","second-person","singular"]},{"form":"büktürtememişti","tags":["inferential","singular","third-person"]},{"form":"büktürtememiştik","tags":["first-person","inferential","plural"]},{"form":"büktürtememiştiniz","tags":["inferential","plural","second-person"]},{"form":"büktürtememişlerdi","tags":["inferential","plural","third-person"]},{"form":"büktürtememişsem","tags":["conditional"]},{"form":"büktürtememişsen","tags":["inferential","second-person","singular"]},{"form":"büktürtememişse","tags":["inferential","singular","third-person"]},{"form":"büktürtememişsek","tags":["first-person","inferential","plural"]},{"form":"büktürtememişseniz","tags":["inferential","plural","second-person"]},{"form":"büktürtememişlerse","tags":["inferential","plural","third-person"]},{"form":"büktürtemeyeceğim","tags":["future","singular","third-person"]},{"form":"büktürtemeyeceksin","tags":["first-person","future","plural"]},{"form":"büktürtemeyecek","tags":["future","plural","second-person"]},{"form":"büktürtemeyeceğiz","tags":["future","plural","third-person"]},{"form":"büktürtemeyeceksiniz","tags":["future"]},{"form":"büktürtemeyecekler","tags":["future"]},{"form":"büktürtemeyecekmişim","tags":["future","inferential"]},{"form":"büktürtemeyecekmişsin","tags":["future","second-person","singular"]},{"form":"büktürtemeyecekmiş","tags":["future","singular","third-person"]},{"form":"büktürtemeyecekmişiz","tags":["first-person","future","plural"]},{"form":"büktürtemeyecekmişsiniz","tags":["future","plural","second-person"]},{"form":"büktürtemeyeceklermiş","tags":["future","plural","third-person"]},{"form":"büktürtemeyecektim","tags":["future","past"]},{"form":"büktürtemeyecektin","tags":["future","second-person","singular"]},{"form":"büktürtemeyecekti","tags":["future","singular","third-person"]},{"form":"büktürtemeyecektik","tags":["first-person","future","plural"]},{"form":"büktürtemeyecektiniz","tags":["future","plural","second-person"]},{"form":"büktürtemeyeceklerdi","tags":["future","plural","third-person"]},{"form":"büktürtemeyeceksem","tags":["conditional","future"]},{"form":"büktürtemeyeceksen","tags":["future","second-person","singular"]},{"form":"büktürtemeyecekse","tags":["future","singular","third-person"]},{"form":"büktürtemeyeceksek","tags":["first-person","future","plural"]},{"form":"büktürtemeyecekseniz","tags":["future","plural","second-person"]},{"form":"büktürtemeyeceklerse","tags":["future","plural","third-person"]},{"form":"büktürtememekteyim","tags":["progressive","singular","third-person"]},{"form":"büktürtememektesin","tags":["first-person","plural","progressive"]},{"form":"büktürtememekte","tags":["plural","progressive","second-person"]},{"form":"büktürtememekteyiz","tags":["plural","progressive","third-person"]},{"form":"büktürtememektesiniz","tags":["progressive"]},{"form":"büktürtememekteler","tags":["progressive"]},{"form":"büktürtememekteymişim","tags":["inferential","progressive"]},{"form":"büktürtememekteymişsin","tags":["progressive","second-person","singular"]},{"form":"büktürtememekteymiş","tags":["progressive","singular","third-person"]},{"form":"büktürtememekteymişiz","tags":["first-person","plural","progressive"]},{"form":"büktürtememekteymişsiniz","tags":["plural","progressive","second-person"]},{"form":"büktürtememektelermiş","tags":["plural","progressive","third-person"]},{"form":"büktürtememekteydim","tags":["past","progressive"]},{"form":"büktürtememekteydin","tags":["progressive","second-person","singular"]},{"form":"büktürtememekteydi","tags":["progressive","singular","third-person"]},{"form":"büktürtememekteydik","tags":["first-person","plural","progressive"]},{"form":"büktürtememekteydiniz","tags":["plural","progressive","second-person"]},{"form":"büktürtememektelerdi","tags":["plural","progressive","third-person"]},{"form":"büktürtememekteysem","tags":["conditional","progressive"]},{"form":"büktürtememekteysen","tags":["progressive","second-person","singular"]},{"form":"büktürtememekteyse","tags":["progressive","singular","third-person"]},{"form":"büktürtememekteysek","tags":["first-person","plural","progressive"]},{"form":"büktürtememekteyseniz","tags":["plural","progressive","second-person"]},{"form":"büktürtememektelerse","tags":["plural","progressive","third-person"]},{"form":"büktürtememeliyim","tags":["necessitative","singular","third-person"]},{"form":"büktürtememelisin","tags":["first-person","necessitative","plural"]},{"form":"büktürtememeli","tags":["necessitative","plural","second-person"]},{"form":"büktürtememeliyiz","tags":["necessitative","plural","third-person"]},{"form":"büktürtememelisiniz","tags":["necessitative"]},{"form":"büktürtememeliler","tags":["necessitative"]},{"form":"büktürtememeliymişim","tags":["inferential"]},{"form":"büktürtememeliymişsin","tags":["necessitative","second-person","singular"]},{"form":"büktürtememeliymiş","tags":["necessitative","singular","third-person"]},{"form":"büktürtememeliymişiz","tags":["first-person","necessitative","plural"]},{"form":"büktürtememeliymişsiniz","tags":["necessitative","plural","second-person"]},{"form":"büktürtememelilermiş","tags":["necessitative","plural","third-person"]},{"form":"büktürtememeliydim","tags":["necessitative","past"]},{"form":"büktürtememeliydin","tags":["necessitative","second-person","singular"]},{"form":"büktürtememeliydi","tags":["necessitative","singular","third-person"]},{"form":"büktürtememeliydik","tags":["first-person","necessitative","plural"]},{"form":"büktürtememeliydiniz","tags":["necessitative","plural","second-person"]},{"form":"büktürtememelilerdi","tags":["necessitative","plural","third-person"]},{"form":"büktürtememeliysem","tags":["conditional"]},{"form":"büktürtememeliysen","tags":["necessitative","second-person","singular"]},{"form":"büktürtememeliyse","tags":["necessitative","singular","third-person"]},{"form":"büktürtememeliysek","tags":["first-person","necessitative","plural"]},{"form":"büktürtememeliyseniz","tags":["necessitative","plural","second-person"]},{"form":"büktürtememelilerse","tags":["necessitative","plural","third-person"]},{"form":"büktürtemedim","tags":["past","singular","third-person"]},{"form":"büktürtemedin","tags":["first-person","past","plural"]},{"form":"büktürtemedi","tags":["past","plural","second-person"]},{"form":"büktürtemedik","tags":["past","plural","third-person"]},{"form":"büktürtemediniz","tags":["past"]},{"form":"büktürtemediler","tags":["past"]},{"form":"büktürtemediysem","tags":["conditional","past"]},{"form":"büktürtemediysen","tags":["past","second-person","singular"]},{"form":"büktürtemediyse","tags":["past","singular","third-person"]},{"form":"büktürtemediysek","tags":["first-person","past","plural"]},{"form":"büktürtemediyseniz","tags":["past","plural","second-person"]},{"form":"büktürtemedilerse","tags":["past","plural","third-person"]},{"form":"büktürtemesem","tags":["conditional","singular","third-person"]},{"form":"büktürtemesen","tags":["conditional","first-person","plural"]},{"form":"büktürtemese","tags":["conditional","plural","second-person"]},{"form":"büktürtemesek","tags":["conditional","plural","third-person"]},{"form":"büktürtemeseniz","tags":["conditional"]},{"form":"büktürtemeseler","tags":["conditional"]},{"form":"büktürtemeseymişim","tags":["inferential"]},{"form":"büktürtemeseymişsin","tags":["conditional","second-person","singular"]},{"form":"büktürtemeseymiş","tags":["conditional","singular","third-person"]},{"form":"büktürtemeseymişiz","tags":["conditional","first-person","plural"]},{"form":"büktürtemeseymişsiniz","tags":["conditional","plural","second-person"]},{"form":"büktürtemeselermiş","tags":["conditional","plural","third-person"]},{"form":"büktürtemeseydim","tags":["conditional","past"]},{"form":"büktürtemeseydin","tags":["conditional","second-person","singular"]},{"form":"büktürtemeseydi","tags":["conditional","singular","third-person"]},{"form":"büktürtemeseydik","tags":["conditional","first-person","plural"]},{"form":"büktürtemeseydiniz","tags":["conditional","plural","second-person"]},{"form":"büktürtemeselerdi","tags":["conditional","plural","third-person"]},{"form":"büktürtemeyeyim","tags":["conditional","optative","singular"]},{"form":"büktürtemeyesin","tags":["optative","second-person","singular"]},{"form":"büktürtemeye","tags":["optative","singular","third-person"]},{"form":"büktürtemeyelim","tags":["first-person","optative","plural"]},{"form":"büktürtemeyesiniz","tags":["optative","plural","second-person"]},{"form":"büktürtemeyeler","tags":["optative","plural","third-person"]},{"form":"-","tags":["imperative","singular","third-person"]},{"form":"büktürteme","tags":["first-person","imperative","plural"]},{"form":"büktürtemesin","tags":["imperative","plural","second-person"]},{"form":"-","tags":["imperative","plural","third-person"]},{"form":"büktürtemeyin","tags":["imperative"]},{"form":"büktürtemesinler","tags":["imperative"]},{"form":"büktürtemeyiniz","tags":["imperative","second-person","singular"]},{"form":"-","tags":["first-person","imperative","plural"]},{"form":"büktürtemeyiniz","tags":["imperative","plural","second-person"]},{"form":"büktürtemesene","tags":["imperative","second-person","singular"]},{"form":"büktürtemesenize","tags":["imperative","plural","second-person"]},{"form":"büktürtememek","tags":["imperative","infinitive"]},{"form":"büktürtememe","tags":["imperative","noun-from-verb"]},{"form":"büktürtemeyen","tags":["imperative","imperfective","impersonal","participle"]},{"form":"büktürtememiş","tags":["imperative","impersonal","participle","perfective"]},{"form":"büktürtemeyecek","tags":["imperative","impersonal","participle","prospective"]},{"form":"büktürtemediğim","tags":["imperative","non-prospective","participle","personal","singular"]},{"form":"büktürtemediğin","tags":["non-prospective","participle","second-person","singular"]},{"form":"büktürtemediği","tags":["non-prospective","participle","singular","third-person"]},{"form":"büktürtemediğimiz","tags":["first-person","non-prospective","participle","plural"]},{"form":"büktürtemediğiniz","tags":["non-prospective","participle","plural","second-person"]},{"form":"büktürtemedikleri","tags":["non-prospective","participle","plural","third-person"]},{"form":"büktürtemeyeceğim","tags":["imperative","participle","personal","prospective","singular"]},{"form":"büktürtemeyeceğin","tags":["participle","prospective","second-person","singular"]},{"form":"büktürtemeyeceği","tags":["participle","prospective","singular","third-person"]},{"form":"büktürtemeyeceğimiz","tags":["first-person","participle","plural","prospective"]},{"form":"büktürtemeyeceğiniz","tags":["participle","plural","prospective","second-person"]},{"form":"büktürtemeyecekleri","tags":["participle","plural","prospective","third-person"]},{"form":"büktürtemezken","tags":["error-unrecognized-form","plural"]},{"form":"büktürtemeyince","tags":["error-unrecognized-form","specific"]},{"form":"büktürtemeyip","tags":["error-unrecognized-form"]},{"form":"büktürtemeyeli","tags":["error-unrecognized-form"]},{"form":"büktürtemeyesiye","tags":["error-unrecognized-form"]},{"form":"büktürtemedikçe","tags":["error-unrecognized-form"]},{"form":"büktürtemeyerek","tags":["error-unrecognized-form","plural"]},{"form":"büktürtemeye büktürtemeye","tags":["error-unrecognized-form"]},{"form":"büktürtemezcesine","tags":["error-unrecognized-form"]}]}