{"word":"sığdırmak","pos":"verb","senses":[{"glosses":["[with dative] to fit (something) into (a container or place)"],"tags":["transitive"],"examples":[{"text":"Bu kitabı çantama sığdıramam.","translation":"I cannot fit this book into my bag."}]}],"etymology":"By surface analysis, sığ- + -dır.","forms":[{"form":"sığdırır","tags":["present","singular","third-person"]},{"form":"no-table-tags","tags":["table-tags"]},{"form":"tr-conj","tags":["inflection-template"]},{"form":"sığdırırım","tags":["aorist","singular","third-person"]},{"form":"sığdırırsın","tags":["aorist","first-person","plural"]},{"form":"sığdırır","tags":["aorist","plural","second-person"]},{"form":"sığdırırız","tags":["aorist","plural","third-person"]},{"form":"sığdırırsınız","tags":["aorist"]},{"form":"sığdırırlar","tags":["aorist"]},{"form":"sığdırırmışım","tags":["aorist","inferential"]},{"form":"sığdırırmışsın","tags":["aorist","second-person","singular"]},{"form":"sığdırırmış","tags":["aorist","singular","third-person"]},{"form":"sığdırırmışız","tags":["aorist","first-person","plural"]},{"form":"sığdırırmışsınız","tags":["aorist","plural","second-person"]},{"form":"sığdırırlarmış","tags":["aorist","plural","third-person"]},{"form":"sığdırırdım","tags":["aorist","past"]},{"form":"sığdırırdın","tags":["aorist","second-person","singular"]},{"form":"sığdırırdı","tags":["aorist","singular","third-person"]},{"form":"sığdırırdık","tags":["aorist","first-person","plural"]},{"form":"sığdırırdınız","tags":["aorist","plural","second-person"]},{"form":"sığdırırlardı","tags":["aorist","plural","third-person"]},{"form":"sığdırırsam","tags":["aorist","conditional"]},{"form":"sığdırırsan","tags":["aorist","second-person","singular"]},{"form":"sığdırırsa","tags":["aorist","singular","third-person"]},{"form":"sığdırırsak","tags":["aorist","first-person","plural"]},{"form":"sığdırırsanız","tags":["aorist","plural","second-person"]},{"form":"sığdırırlarsa","tags":["aorist","plural","third-person"]},{"form":"sığdırıyorum","tags":["continuative","singular","third-person"]},{"form":"sığdırıyorsun","tags":["continuative","first-person","plural"]},{"form":"sığdırıyor","tags":["continuative","plural","second-person"]},{"form":"sığdırıyoruz","tags":["continuative","plural","third-person"]},{"form":"sığdırıyorsunuz","tags":["continuative"]},{"form":"sığdırıyorlar","tags":["continuative"]},{"form":"sığdırıyormuşum","tags":["continuative","inferential"]},{"form":"sığdırıyormuşsun","tags":["continuative","second-person","singular"]},{"form":"sığdırıyormuş","tags":["continuative","singular","third-person"]},{"form":"sığdırıyormuşuz","tags":["continuative","first-person","plural"]},{"form":"sığdırıyormuşsunuz","tags":["continuative","plural","second-person"]},{"form":"sığdırıyorlarmış","tags":["continuative","plural","third-person"]},{"form":"sığdırıyordum","tags":["continuative","past"]},{"form":"sığdırıyordun","tags":["continuative","second-person","singular"]},{"form":"sığdırıyordu","tags":["continuative","singular","third-person"]},{"form":"sığdırıyorduk","tags":["continuative","first-person","plural"]},{"form":"sığdırıyordunuz","tags":["continuative","plural","second-person"]},{"form":"sığdırıyorlardı","tags":["continuative","plural","third-person"]},{"form":"sığdırıyorsam","tags":["conditional","continuative"]},{"form":"sığdırıyorsan","tags":["continuative","second-person","singular"]},{"form":"sığdırıyorsa","tags":["continuative","singular","third-person"]},{"form":"sığdırıyorsak","tags":["continuative","first-person","plural"]},{"form":"sığdırıyorsanız","tags":["continuative","plural","second-person"]},{"form":"sığdırıyorlarsa","tags":["continuative","plural","third-person"]},{"form":"sığdırmışım","tags":["inferential","singular","third-person"]},{"form":"sığdırmışsın","tags":["first-person","inferential","plural"]},{"form":"sığdırmış","tags":["inferential","plural","second-person"]},{"form":"sığdırmışız","tags":["inferential","plural","third-person"]},{"form":"sığdırmışsınız","tags":["inferential"]},{"form":"sığdırmışlar","tags":["inferential"]},{"form":"sığdırmışmışım","tags":["inferential"]},{"form":"sığdırmışmışsın","tags":["inferential","second-person","singular"]},{"form":"sığdırmışmış","tags":["inferential","singular","third-person"]},{"form":"sığdırmışmışız","tags":["first-person","inferential","plural"]},{"form":"sığdırmışmışsınız","tags":["inferential","plural","second-person"]},{"form":"sığdırmışlarmış","tags":["inferential","plural","third-person"]},{"form":"sığdırmıştım","tags":["inferential","past"]},{"form":"sığdırmıştın","tags":["inferential","second-person","singular"]},{"form":"sığdırmıştı","tags":["inferential","singular","third-person"]},{"form":"sığdırmıştık","tags":["first-person","inferential","plural"]},{"form":"sığdırmıştınız","tags":["inferential","plural","second-person"]},{"form":"sığdırmışlardı","tags":["inferential","plural","third-person"]},{"form":"sığdırmışsam","tags":["conditional"]},{"form":"sığdırmışsan","tags":["inferential","second-person","singular"]},{"form":"sığdırmışsa","tags":["inferential","singular","third-person"]},{"form":"sığdırmışsak","tags":["first-person","inferential","plural"]},{"form":"sığdırmışsanız","tags":["inferential","plural","second-person"]},{"form":"sığdırmışlarsa","tags":["inferential","plural","third-person"]},{"form":"sığdıracağım","tags":["future","singular","third-person"]},{"form":"sığdıracaksın","tags":["first-person","future","plural"]},{"form":"sığdıracak","tags":["future","plural","second-person"]},{"form":"sığdıracağız","tags":["future","plural","third-person"]},{"form":"sığdıracaksınız","tags":["future"]},{"form":"sığdıracaklar","tags":["future"]},{"form":"sığdıracakmışım","tags":["future","inferential"]},{"form":"sığdıracakmışsın","tags":["future","second-person","singular"]},{"form":"sığdıracakmış","tags":["future","singular","third-person"]},{"form":"sığdıracakmışız","tags":["first-person","future","plural"]},{"form":"sığdıracakmışsınız","tags":["future","plural","second-person"]},{"form":"sığdıracaklarmış","tags":["future","plural","third-person"]},{"form":"sığdıracaktım","tags":["future","past"]},{"form":"sığdıracaktın","tags":["future","second-person","singular"]},{"form":"sığdıracaktı","tags":["future","singular","third-person"]},{"form":"sığdıracaktık","tags":["first-person","future","plural"]},{"form":"sığdıracaktınız","tags":["future","plural","second-person"]},{"form":"sığdıracaklardı","tags":["future","plural","third-person"]},{"form":"sığdıracaksam","tags":["conditional","future"]},{"form":"sığdıracaksan","tags":["future","second-person","singular"]},{"form":"sığdıracaksa","tags":["future","singular","third-person"]},{"form":"sığdıracaksak","tags":["first-person","future","plural"]},{"form":"sığdıracaksanız","tags":["future","plural","second-person"]},{"form":"sığdıracaklarsa","tags":["future","plural","third-person"]},{"form":"sığdırmaktayım","tags":["progressive","singular","third-person"]},{"form":"sığdırmaktasın","tags":["first-person","plural","progressive"]},{"form":"sığdırmakta","tags":["plural","progressive","second-person"]},{"form":"sığdırmaktayız","tags":["plural","progressive","third-person"]},{"form":"sığdırmaktasınız","tags":["progressive"]},{"form":"sığdırmaktalar","tags":["progressive"]},{"form":"sığdırmaktaymışım","tags":["inferential","progressive"]},{"form":"sığdırmaktaymışsın","tags":["progressive","second-person","singular"]},{"form":"sığdırmaktaymış","tags":["progressive","singular","third-person"]},{"form":"sığdırmaktaymışız","tags":["first-person","plural","progressive"]},{"form":"sığdırmaktaymışsınız","tags":["plural","progressive","second-person"]},{"form":"sığdırmaktalarmış","tags":["plural","progressive","third-person"]},{"form":"sığdırmaktaydım","tags":["past","progressive"]},{"form":"sığdırmaktaydın","tags":["progressive","second-person","singular"]},{"form":"sığdırmaktaydı","tags":["progressive","singular","third-person"]},{"form":"sığdırmaktaydık","tags":["first-person","plural","progressive"]},{"form":"sığdırmaktaydınız","tags":["plural","progressive","second-person"]},{"form":"sığdırmaktalardı","tags":["plural","progressive","third-person"]},{"form":"sığdırmaktaysam","tags":["conditional","progressive"]},{"form":"sığdırmaktaysan","tags":["progressive","second-person","singular"]},{"form":"sığdırmaktaysa","tags":["progressive","singular","third-person"]},{"form":"sığdırmaktaysak","tags":["first-person","plural","progressive"]},{"form":"sığdırmaktaysanız","tags":["plural","progressive","second-person"]},{"form":"sığdırmaktalarsa","tags":["plural","progressive","third-person"]},{"form":"sığdırmalıyım","tags":["necessitative","singular","third-person"]},{"form":"sığdırmalısın","tags":["first-person","necessitative","plural"]},{"form":"sığdırmalı","tags":["necessitative","plural","second-person"]},{"form":"sığdırmalıyız","tags":["necessitative","plural","third-person"]},{"form":"sığdırmalısınız","tags":["necessitative"]},{"form":"sığdırmalılar","tags":["necessitative"]},{"form":"sığdırmalıymışım","tags":["inferential"]},{"form":"sığdırmalıymışsın","tags":["necessitative","second-person","singular"]},{"form":"sığdırmalıymış","tags":["necessitative","singular","third-person"]},{"form":"sığdırmalıymışız","tags":["first-person","necessitative","plural"]},{"form":"sığdırmalıymışsınız","tags":["necessitative","plural","second-person"]},{"form":"sığdırmalılarmış","tags":["necessitative","plural","third-person"]},{"form":"sığdırmalıydım","tags":["necessitative","past"]},{"form":"sığdırmalıydın","tags":["necessitative","second-person","singular"]},{"form":"sığdırmalıydı","tags":["necessitative","singular","third-person"]},{"form":"sığdırmalıydık","tags":["first-person","necessitative","plural"]},{"form":"sığdırmalıydınız","tags":["necessitative","plural","second-person"]},{"form":"sığdırmalılardı","tags":["necessitative","plural","third-person"]},{"form":"sığdırmalıysam","tags":["conditional"]},{"form":"sığdırmalıysan","tags":["necessitative","second-person","singular"]},{"form":"sığdırmalıysa","tags":["necessitative","singular","third-person"]},{"form":"sığdırmalıysak","tags":["first-person","necessitative","plural"]},{"form":"sığdırmalıysanız","tags":["necessitative","plural","second-person"]},{"form":"sığdırmalılarsa","tags":["necessitative","plural","third-person"]},{"form":"sığdırdım","tags":["past","singular","third-person"]},{"form":"sığdırdın","tags":["first-person","past","plural"]},{"form":"sığdırdı","tags":["past","plural","second-person"]},{"form":"sığdırdık","tags":["past","plural","third-person"]},{"form":"sığdırdınız","tags":["past"]},{"form":"sığdırdılar","tags":["past"]},{"form":"sığdırdıysam","tags":["conditional","past"]},{"form":"sığdırdıysan","tags":["past","second-person","singular"]},{"form":"sığdırdıysa","tags":["past","singular","third-person"]},{"form":"sığdırdıysak","tags":["first-person","past","plural"]},{"form":"sığdırdıysanız","tags":["past","plural","second-person"]},{"form":"sığdırdılarsa","tags":["past","plural","third-person"]},{"form":"sığdırsam","tags":["conditional","singular","third-person"]},{"form":"sığdırsan","tags":["conditional","first-person","plural"]},{"form":"sığdırsa","tags":["conditional","plural","second-person"]},{"form":"sığdırsak","tags":["conditional","plural","third-person"]},{"form":"sığdırsanız","tags":["conditional"]},{"form":"sığdırsalar","tags":["conditional"]},{"form":"sığdırsaymışım","tags":["inferential"]},{"form":"sığdırsaymışsın","tags":["conditional","second-person","singular"]},{"form":"sığdırsaymış","tags":["conditional","singular","third-person"]},{"form":"sığdırsaymışız","tags":["conditional","first-person","plural"]},{"form":"sığdırsaymışsınız","tags":["conditional","plural","second-person"]},{"form":"sığdırsalarmış","tags":["conditional","plural","third-person"]},{"form":"sığdırsaydım","tags":["conditional","past"]},{"form":"sığdırsaydın","tags":["conditional","second-person","singular"]},{"form":"sığdırsaydı","tags":["conditional","singular","third-person"]},{"form":"sığdırsaydık","tags":["conditional","first-person","plural"]},{"form":"sığdırsaydınız","tags":["conditional","plural","second-person"]},{"form":"sığdırsalardı","tags":["conditional","plural","third-person"]},{"form":"sığdırayım","tags":["conditional","optative","singular"]},{"form":"sığdırasın","tags":["optative","second-person","singular"]},{"form":"sığdıra","tags":["optative","singular","third-person"]},{"form":"sığdıralım","tags":["first-person","optative","plural"]},{"form":"sığdırasınız","tags":["optative","plural","second-person"]},{"form":"sığdıralar","tags":["optative","plural","third-person"]},{"form":"-","tags":["imperative","singular","third-person"]},{"form":"sığdır","tags":["first-person","imperative","plural"]},{"form":"sığdırsın","tags":["imperative","plural","second-person"]},{"form":"-","tags":["imperative","plural","third-person"]},{"form":"sığdırın","tags":["imperative"]},{"form":"sığdırsınlar","tags":["imperative"]},{"form":"sığdırınız","tags":["imperative","second-person","singular"]},{"form":"-","tags":["first-person","imperative","plural"]},{"form":"sığdırınız","tags":["imperative","plural","second-person"]},{"form":"sığdırsana","tags":["imperative","second-person","singular"]},{"form":"sığdırsanıza","tags":["imperative","plural","second-person"]},{"form":"sığdırmak","tags":["imperative","infinitive"]},{"form":"sığdırma","tags":["imperative","noun-from-verb"]},{"form":"sığdıran","tags":["imperative","imperfective","impersonal","participle"]},{"form":"sığdırmış","tags":["imperative","impersonal","participle","perfective"]},{"form":"sığdıracak","tags":["imperative","impersonal","participle","prospective"]},{"form":"sığdırdığım","tags":["imperative","non-prospective","participle","personal","singular"]},{"form":"sığdırdığın","tags":["non-prospective","participle","second-person","singular"]},{"form":"sığdırdığı","tags":["non-prospective","participle","singular","third-person"]},{"form":"sığdırdığımız","tags":["first-person","non-prospective","participle","plural"]},{"form":"sığdırdığınız","tags":["non-prospective","participle","plural","second-person"]},{"form":"sığdırdıkları","tags":["non-prospective","participle","plural","third-person"]},{"form":"sığdıracağım","tags":["imperative","participle","personal","prospective","singular"]},{"form":"sığdıracağın","tags":["participle","prospective","second-person","singular"]},{"form":"sığdıracağı","tags":["participle","prospective","singular","third-person"]},{"form":"sığdıracağımız","tags":["first-person","participle","plural","prospective"]},{"form":"sığdıracağınız","tags":["participle","plural","prospective","second-person"]},{"form":"sığdıracakları","tags":["participle","plural","prospective","third-person"]},{"form":"sığdırırken","tags":["error-unrecognized-form","plural"]},{"form":"sığdırınca","tags":["error-unrecognized-form","specific"]},{"form":"sığdırıp","tags":["error-unrecognized-form"]},{"form":"sığdıralı","tags":["error-unrecognized-form"]},{"form":"sığdırasıya","tags":["error-unrecognized-form"]},{"form":"sığdırdıkça","tags":["error-unrecognized-form"]},{"form":"sığdırarak","tags":["error-unrecognized-form","plural"]},{"form":"sığdıra sığdıra","tags":["error-unrecognized-form"]},{"form":"sığdırırcasına","tags":["error-unrecognized-form"]},{"form":"negative","tags":["table-tags"]},{"form":"tr-conj","tags":["inflection-template"]},{"form":"sığdırmam","tags":["aorist","negative","singular","third-person"]},{"form":"sığdırmazsın","tags":["aorist","first-person","negative","plural"]},{"form":"sığdırmaz","tags":["aorist","negative","plural","second-person"]},{"form":"sığdırmayız","tags":["aorist","negative","plural","third-person"]},{"form":"sığdırmazsınız","tags":["aorist","negative"]},{"form":"sığdırmazlar","tags":["aorist","negative"]},{"form":"sığdırmazmışım","tags":["aorist","inferential","negative"]},{"form":"sığdırmazmışsın","tags":["aorist","negative","second-person","singular"]},{"form":"sığdırmazmış","tags":["aorist","negative","singular","third-person"]},{"form":"sığdırmazmışız","tags":["aorist","first-person","negative","plural"]},{"form":"sığdırmazmışsınız","tags":["aorist","negative","plural","second-person"]},{"form":"sığdırmazlarmış","tags":["aorist","negative","plural","third-person"]},{"form":"sığdırmazdım","tags":["aorist","negative","past"]},{"form":"sığdırmazdın","tags":["aorist","negative","second-person","singular"]},{"form":"sığdırmazdı","tags":["aorist","negative","singular","third-person"]},{"form":"sığdırmazdık","tags":["aorist","first-person","negative","plural"]},{"form":"sığdırmazdınız","tags":["aorist","negative","plural","second-person"]},{"form":"sığdırmazlardı","tags":["aorist","negative","plural","third-person"]},{"form":"sığdırmazsam","tags":["aorist","conditional","negative"]},{"form":"sığdırmazsan","tags":["aorist","negative","second-person","singular"]},{"form":"sığdırmazsa","tags":["aorist","negative","singular","third-person"]},{"form":"sığdırmazsak","tags":["aorist","first-person","negative","plural"]},{"form":"sığdırmazsanız","tags":["aorist","negative","plural","second-person"]},{"form":"sığdırmazlarsa","tags":["aorist","negative","plural","third-person"]},{"form":"sığdırmıyorum","tags":["continuative","negative","singular","third-person"]},{"form":"sığdırmıyorsun","tags":["continuative","first-person","negative","plural"]},{"form":"sığdırmıyor","tags":["continuative","negative","plural","second-person"]},{"form":"sığdırmıyoruz","tags":["continuative","negative","plural","third-person"]},{"form":"sığdırmıyorsunuz","tags":["continuative","negative"]},{"form":"sığdırmıyorlar","tags":["continuative","negative"]},{"form":"sığdırmıyormuşum","tags":["continuative","inferential","negative"]},{"form":"sığdırmıyormuşsun","tags":["continuative","negative","second-person","singular"]},{"form":"sığdırmıyormuş","tags":["continuative","negative","singular","third-person"]},{"form":"sığdırmıyormuşuz","tags":["continuative","first-person","negative","plural"]},{"form":"sığdırmıyormuşsunuz","tags":["continuative","negative","plural","second-person"]},{"form":"sığdırmıyorlarmış","tags":["continuative","negative","plural","third-person"]},{"form":"sığdırmıyordum","tags":["continuative","negative","past"]},{"form":"sığdırmıyordun","tags":["continuative","negative","second-person","singular"]},{"form":"sığdırmıyordu","tags":["continuative","negative","singular","third-person"]},{"form":"sığdırmıyorduk","tags":["continuative","first-person","negative","plural"]},{"form":"sığdırmıyordunuz","tags":["continuative","negative","plural","second-person"]},{"form":"sığdırmıyorlardı","tags":["continuative","negative","plural","third-person"]},{"form":"sığdırmıyorsam","tags":["conditional","continuative","negative"]},{"form":"sığdırmıyorsan","tags":["continuative","negative","second-person","singular"]},{"form":"sığdırmıyorsa","tags":["continuative","negative","singular","third-person"]},{"form":"sığdırmıyorsak","tags":["continuative","first-person","negative","plural"]},{"form":"sığdırmıyorsanız","tags":["continuative","negative","plural","second-person"]},{"form":"sığdırmıyorlarsa","tags":["continuative","negative","plural","third-person"]},{"form":"sığdırmamışım","tags":["inferential","negative","singular","third-person"]},{"form":"sığdırmamışsın","tags":["first-person","inferential","negative","plural"]},{"form":"sığdırmamış","tags":["inferential","negative","plural","second-person"]},{"form":"sığdırmamışız","tags":["inferential","negative","plural","third-person"]},{"form":"sığdırmamışsınız","tags":["inferential","negative"]},{"form":"sığdırmamışlar","tags":["inferential","negative"]},{"form":"sığdırmamışmışım","tags":["inferential","negative"]},{"form":"sığdırmamışmışsın","tags":["inferential","negative","second-person","singular"]},{"form":"sığdırmamışmış","tags":["inferential","negative","singular","third-person"]},{"form":"sığdırmamışmışız","tags":["first-person","inferential","negative","plural"]},{"form":"sığdırmamışmışsınız","tags":["inferential","negative","plural","second-person"]},{"form":"sığdırmamışlarmış","tags":["inferential","negative","plural","third-person"]},{"form":"sığdırmamıştım","tags":["inferential","negative","past"]},{"form":"sığdırmamıştın","tags":["inferential","negative","second-person","singular"]},{"form":"sığdırmamıştı","tags":["inferential","negative","singular","third-person"]},{"form":"sığdırmamıştık","tags":["first-person","inferential","negative","plural"]},{"form":"sığdırmamıştınız","tags":["inferential","negative","plural","second-person"]},{"form":"sığdırmamışlardı","tags":["inferential","negative","plural","third-person"]},{"form":"sığdırmamışsam","tags":["conditional","negative"]},{"form":"sığdırmamışsan","tags":["inferential","negative","second-person","singular"]},{"form":"sığdırmamışsa","tags":["inferential","negative","singular","third-person"]},{"form":"sığdırmamışsak","tags":["first-person","inferential","negative","plural"]},{"form":"sığdırmamışsanız","tags":["inferential","negative","plural","second-person"]},{"form":"sığdırmamışlarsa","tags":["inferential","negative","plural","third-person"]},{"form":"sığdırmayacağım","tags":["future","negative","singular","third-person"]},{"form":"sığdırmayacaksın","tags":["first-person","future","negative","plural"]},{"form":"sığdırmayacak","tags":["future","negative","plural","second-person"]},{"form":"sığdırmayacağız","tags":["future","negative","plural","third-person"]},{"form":"sığdırmayacaksınız","tags":["future","negative"]},{"form":"sığdırmayacaklar","tags":["future","negative"]},{"form":"sığdırmayacakmışım","tags":["future","inferential","negative"]},{"form":"sığdırmayacakmışsın","tags":["future","negative","second-person","singular"]},{"form":"sığdırmayacakmış","tags":["future","negative","singular","third-person"]},{"form":"sığdırmayacakmışız","tags":["first-person","future","negative","plural"]},{"form":"sığdırmayacakmışsınız","tags":["future","negative","plural","second-person"]},{"form":"sığdırmayacaklarmış","tags":["future","negative","plural","third-person"]},{"form":"sığdırmayacaktım","tags":["future","negative","past"]},{"form":"sığdırmayacaktın","tags":["future","negative","second-person","singular"]},{"form":"sığdırmayacaktı","tags":["future","negative","singular","third-person"]},{"form":"sığdırmayacaktık","tags":["first-person","future","negative","plural"]},{"form":"sığdırmayacaktınız","tags":["future","negative","plural","second-person"]},{"form":"sığdırmayacaklardı","tags":["future","negative","plural","third-person"]},{"form":"sığdırmayacaksam","tags":["conditional","future","negative"]},{"form":"sığdırmayacaksan","tags":["future","negative","second-person","singular"]},{"form":"sığdırmayacaksa","tags":["future","negative","singular","third-person"]},{"form":"sığdırmayacaksak","tags":["first-person","future","negative","plural"]},{"form":"sığdırmayacaksanız","tags":["future","negative","plural","second-person"]},{"form":"sığdırmayacaklarsa","tags":["future","negative","plural","third-person"]},{"form":"sığdırmamaktayım","tags":["negative","progressive","singular","third-person"]},{"form":"sığdırmamaktasın","tags":["first-person","negative","plural","progressive"]},{"form":"sığdırmamakta","tags":["negative","plural","progressive","second-person"]},{"form":"sığdırmamaktayız","tags":["negative","plural","progressive","third-person"]},{"form":"sığdırmamaktasınız","tags":["negative","progressive"]},{"form":"sığdırmamaktalar","tags":["negative","progressive"]},{"form":"sığdırmamaktaymışım","tags":["inferential","negative","progressive"]},{"form":"sığdırmamaktaymışsın","tags":["negative","progressive","second-person","singular"]},{"form":"sığdırmamaktaymış","tags":["negative","progressive","singular","third-person"]},{"form":"sığdırmamaktaymışız","tags":["first-person","negative","plural","progressive"]},{"form":"sığdırmamaktaymışsınız","tags":["negative","plural","progressive","second-person"]},{"form":"sığdırmamaktalarmış","tags":["negative","plural","progressive","third-person"]},{"form":"sığdırmamaktaydım","tags":["negative","past","progressive"]},{"form":"sığdırmamaktaydın","tags":["negative","progressive","second-person","singular"]},{"form":"sığdırmamaktaydı","tags":["negative","progressive","singular","third-person"]},{"form":"sığdırmamaktaydık","tags":["first-person","negative","plural","progressive"]},{"form":"sığdırmamaktaydınız","tags":["negative","plural","progressive","second-person"]},{"form":"sığdırmamaktalardı","tags":["negative","plural","progressive","third-person"]},{"form":"sığdırmamaktaysam","tags":["conditional","negative","progressive"]},{"form":"sığdırmamaktaysan","tags":["negative","progressive","second-person","singular"]},{"form":"sığdırmamaktaysa","tags":["negative","progressive","singular","third-person"]},{"form":"sığdırmamaktaysak","tags":["first-person","negative","plural","progressive"]},{"form":"sığdırmamaktaysanız","tags":["negative","plural","progressive","second-person"]},{"form":"sığdırmamaktalarsa","tags":["negative","plural","progressive","third-person"]},{"form":"sığdırmamalıyım","tags":["necessitative","negative","singular","third-person"]},{"form":"sığdırmamalısın","tags":["first-person","necessitative","negative","plural"]},{"form":"sığdırmamalı","tags":["necessitative","negative","plural","second-person"]},{"form":"sığdırmamalıyız","tags":["necessitative","negative","plural","third-person"]},{"form":"sığdırmamalısınız","tags":["necessitative","negative"]},{"form":"sığdırmamalılar","tags":["necessitative","negative"]},{"form":"sığdırmamalıymışım","tags":["inferential","negative"]},{"form":"sığdırmamalıymışsın","tags":["necessitative","negative","second-person","singular"]},{"form":"sığdırmamalıymış","tags":["necessitative","negative","singular","third-person"]},{"form":"sığdırmamalıymışız","tags":["first-person","necessitative","negative","plural"]},{"form":"sığdırmamalıymışsınız","tags":["necessitative","negative","plural","second-person"]},{"form":"sığdırmamalılarmış","tags":["necessitative","negative","plural","third-person"]},{"form":"sığdırmamalıydım","tags":["necessitative","negative","past"]},{"form":"sığdırmamalıydın","tags":["necessitative","negative","second-person","singular"]},{"form":"sığdırmamalıydı","tags":["necessitative","negative","singular","third-person"]},{"form":"sığdırmamalıydık","tags":["first-person","necessitative","negative","plural"]},{"form":"sığdırmamalıydınız","tags":["necessitative","negative","plural","second-person"]},{"form":"sığdırmamalılardı","tags":["necessitative","negative","plural","third-person"]},{"form":"sığdırmamalıysam","tags":["conditional","negative"]},{"form":"sığdırmamalıysan","tags":["necessitative","negative","second-person","singular"]},{"form":"sığdırmamalıysa","tags":["necessitative","negative","singular","third-person"]},{"form":"sığdırmamalıysak","tags":["first-person","necessitative","negative","plural"]},{"form":"sığdırmamalıysanız","tags":["necessitative","negative","plural","second-person"]},{"form":"sığdırmamalılarsa","tags":["necessitative","negative","plural","third-person"]},{"form":"sığdırmadım","tags":["negative","past","singular","third-person"]},{"form":"sığdırmadın","tags":["first-person","negative","past","plural"]},{"form":"sığdırmadı","tags":["negative","past","plural","second-person"]},{"form":"sığdırmadık","tags":["negative","past","plural","third-person"]},{"form":"sığdırmadınız","tags":["negative","past"]},{"form":"sığdırmadılar","tags":["negative","past"]},{"form":"sığdırmadıysam","tags":["conditional","negative","past"]},{"form":"sığdırmadıysan","tags":["negative","past","second-person","singular"]},{"form":"sığdırmadıysa","tags":["negative","past","singular","third-person"]},{"form":"sığdırmadıysak","tags":["first-person","negative","past","plural"]},{"form":"sığdırmadıysanız","tags":["negative","past","plural","second-person"]},{"form":"sığdırmadılarsa","tags":["negative","past","plural","third-person"]},{"form":"sığdırmasam","tags":["conditional","negative","singular","third-person"]},{"form":"sığdırmasan","tags":["conditional","first-person","negative","plural"]},{"form":"sığdırmasa","tags":["conditional","negative","plural","second-person"]},{"form":"sığdırmasak","tags":["conditional","negative","plural","third-person"]},{"form":"sığdırmasanız","tags":["conditional","negative"]},{"form":"sığdırmasalar","tags":["conditional","negative"]},{"form":"sığdırmasaymışım","tags":["inferential","negative"]},{"form":"sığdırmasaymışsın","tags":["conditional","negative","second-person","singular"]},{"form":"sığdırmasaymış","tags":["conditional","negative","singular","third-person"]},{"form":"sığdırmasaymışız","tags":["conditional","first-person","negative","plural"]},{"form":"sığdırmasaymışsınız","tags":["conditional","negative","plural","second-person"]},{"form":"sığdırmasalarmış","tags":["conditional","negative","plural","third-person"]},{"form":"sığdırmasaydım","tags":["conditional","negative","past"]},{"form":"sığdırmasaydın","tags":["conditional","negative","second-person","singular"]},{"form":"sığdırmasaydı","tags":["conditional","negative","singular","third-person"]},{"form":"sığdırmasaydık","tags":["conditional","first-person","negative","plural"]},{"form":"sığdırmasaydınız","tags":["conditional","negative","plural","second-person"]},{"form":"sığdırmasalardı","tags":["conditional","negative","plural","third-person"]},{"form":"sığdırmayayım","tags":["conditional","negative","optative","singular"]},{"form":"sığdırmayasın","tags":["negative","optative","second-person","singular"]},{"form":"sığdırmaya","tags":["negative","optative","singular","third-person"]},{"form":"sığdırmayalım","tags":["first-person","negative","optative","plural"]},{"form":"sığdırmayasınız","tags":["negative","optative","plural","second-person"]},{"form":"sığdırmayalar","tags":["negative","optative","plural","third-person"]},{"form":"-","tags":["imperative","negative","singular","third-person"]},{"form":"sığdırma","tags":["first-person","imperative","negative","plural"]},{"form":"sığdırmasın","tags":["imperative","negative","plural","second-person"]},{"form":"-","tags":["imperative","negative","plural","third-person"]},{"form":"sığdırmayın","tags":["imperative","negative"]},{"form":"sığdırmasınlar","tags":["imperative","negative"]},{"form":"sığdırmayınız","tags":["imperative","negative","second-person","singular"]},{"form":"-","tags":["first-person","imperative","negative","plural"]},{"form":"sığdırmayınız","tags":["imperative","negative","plural","second-person"]},{"form":"sığdırmasana","tags":["imperative","negative","second-person","singular"]},{"form":"sığdırmasanıza","tags":["imperative","negative","plural","second-person"]},{"form":"sığdırmamak","tags":["imperative","infinitive","negative"]},{"form":"sığdırmama","tags":["imperative","negative","noun-from-verb"]},{"form":"sığdırmayan","tags":["imperative","imperfective","impersonal","negative","participle"]},{"form":"sığdırmamış","tags":["imperative","impersonal","negative","participle","perfective"]},{"form":"sığdırmayacak","tags":["imperative","impersonal","negative","participle","prospective"]},{"form":"sığdırmadığım","tags":["imperative","negative","non-prospective","participle","personal","singular"]},{"form":"sığdırmadığın","tags":["negative","non-prospective","participle","second-person","singular"]},{"form":"sığdırmadığı","tags":["negative","non-prospective","participle","singular","third-person"]},{"form":"sığdırmadığımız","tags":["first-person","negative","non-prospective","participle","plural"]},{"form":"sığdırmadığınız","tags":["negative","non-prospective","participle","plural","second-person"]},{"form":"sığdırmadıkları","tags":["negative","non-prospective","participle","plural","third-person"]},{"form":"sığdırmayacağım","tags":["imperative","negative","participle","personal","prospective","singular"]},{"form":"sığdırmayacağın","tags":["negative","participle","prospective","second-person","singular"]},{"form":"sığdırmayacağı","tags":["negative","participle","prospective","singular","third-person"]},{"form":"sığdırmayacağımız","tags":["first-person","negative","participle","plural","prospective"]},{"form":"sığdırmayacağınız","tags":["negative","participle","plural","prospective","second-person"]},{"form":"sığdırmayacakları","tags":["negative","participle","plural","prospective","third-person"]},{"form":"sığdırmazken","tags":["error-unrecognized-form","negative","plural"]},{"form":"sığdırmayınca","tags":["error-unrecognized-form","negative","specific"]},{"form":"sığdırmayıp","tags":["error-unrecognized-form","negative"]},{"form":"sığdırmayalı","tags":["error-unrecognized-form","negative"]},{"form":"sığdırmayasıya","tags":["error-unrecognized-form","negative"]},{"form":"sığdırmadıkça","tags":["error-unrecognized-form","negative"]},{"form":"sığdırmayarak","tags":["error-unrecognized-form","negative","plural"]},{"form":"sığdırmaya sığdırmaya","tags":["error-unrecognized-form","negative"]},{"form":"sığdırmazcasına","tags":["error-unrecognized-form","negative"]},{"form":"no-table-tags","tags":["table-tags"]},{"form":"tr-conj","tags":["inflection-template"]},{"form":"sığdırabilirim","tags":["aorist","singular","third-person"]},{"form":"sığdırabilirsin","tags":["aorist","first-person","plural"]},{"form":"sığdırabilir","tags":["aorist","plural","second-person"]},{"form":"sığdırabiliriz","tags":["aorist","plural","third-person"]},{"form":"sığdırabilirsiniz","tags":["aorist"]},{"form":"sığdırabilirler","tags":["aorist"]},{"form":"sığdırabilirmişim","tags":["aorist","inferential"]},{"form":"sığdırabilirmişsin","tags":["aorist","second-person","singular"]},{"form":"sığdırabilirmiş","tags":["aorist","singular","third-person"]},{"form":"sığdırabilirmişiz","tags":["aorist","first-person","plural"]},{"form":"sığdırabilirmişsiniz","tags":["aorist","plural","second-person"]},{"form":"sığdırabilirlermiş","tags":["aorist","plural","third-person"]},{"form":"sığdırabilirdim","tags":["aorist","past"]},{"form":"sığdırabilirdin","tags":["aorist","second-person","singular"]},{"form":"sığdırabilirdi","tags":["aorist","singular","third-person"]},{"form":"sığdırabilirdik","tags":["aorist","first-person","plural"]},{"form":"sığdırabilirdiniz","tags":["aorist","plural","second-person"]},{"form":"sığdırabilirlerdi","tags":["aorist","plural","third-person"]},{"form":"sığdırabilirsem","tags":["aorist","conditional"]},{"form":"sığdırabilirsen","tags":["aorist","second-person","singular"]},{"form":"sığdırabilirse","tags":["aorist","singular","third-person"]},{"form":"sığdırabilirsek","tags":["aorist","first-person","plural"]},{"form":"sığdırabilirseniz","tags":["aorist","plural","second-person"]},{"form":"sığdırabilirlerse","tags":["aorist","plural","third-person"]},{"form":"sığdırabiliyorum","tags":["continuative","singular","third-person"]},{"form":"sığdırabiliyorsun","tags":["continuative","first-person","plural"]},{"form":"sığdırabiliyor","tags":["continuative","plural","second-person"]},{"form":"sığdırabiliyoruz","tags":["continuative","plural","third-person"]},{"form":"sığdırabiliyorsunuz","tags":["continuative"]},{"form":"sığdırabiliyorlar","tags":["continuative"]},{"form":"sığdırabiliyormuşum","tags":["continuative","inferential"]},{"form":"sığdırabiliyormuşsun","tags":["continuative","second-person","singular"]},{"form":"sığdırabiliyormuş","tags":["continuative","singular","third-person"]},{"form":"sığdırabiliyormuşuz","tags":["continuative","first-person","plural"]},{"form":"sığdırabiliyormuşsunuz","tags":["continuative","plural","second-person"]},{"form":"sığdırabiliyorlarmış","tags":["continuative","plural","third-person"]},{"form":"sığdırabiliyordum","tags":["continuative","past"]},{"form":"sığdırabiliyordun","tags":["continuative","second-person","singular"]},{"form":"sığdırabiliyordu","tags":["continuative","singular","third-person"]},{"form":"sığdırabiliyorduk","tags":["continuative","first-person","plural"]},{"form":"sığdırabiliyordunuz","tags":["continuative","plural","second-person"]},{"form":"sığdırabiliyorlardı","tags":["continuative","plural","third-person"]},{"form":"sığdırabiliyorsam","tags":["conditional","continuative"]},{"form":"sığdırabiliyorsan","tags":["continuative","second-person","singular"]},{"form":"sığdırabiliyorsa","tags":["continuative","singular","third-person"]},{"form":"sığdırabiliyorsak","tags":["continuative","first-person","plural"]},{"form":"sığdırabiliyorsanız","tags":["continuative","plural","second-person"]},{"form":"sığdırabiliyorlarsa","tags":["continuative","plural","third-person"]},{"form":"sığdırabilmişim","tags":["inferential","singular","third-person"]},{"form":"sığdırabilmişsin","tags":["first-person","inferential","plural"]},{"form":"sığdırabilmiş","tags":["inferential","plural","second-person"]},{"form":"sığdırabilmişiz","tags":["inferential","plural","third-person"]},{"form":"sığdırabilmişsiniz","tags":["inferential"]},{"form":"sığdırabilmişler","tags":["inferential"]},{"form":"sığdırabilmişmişim","tags":["inferential"]},{"form":"sığdırabilmişmişsin","tags":["inferential","second-person","singular"]},{"form":"sığdırabilmişmiş","tags":["inferential","singular","third-person"]},{"form":"sığdırabilmişmişiz","tags":["first-person","inferential","plural"]},{"form":"sığdırabilmişmişsiniz","tags":["inferential","plural","second-person"]},{"form":"sığdırabilmişlermiş","tags":["inferential","plural","third-person"]},{"form":"sığdırabilmiştim","tags":["inferential","past"]},{"form":"sığdırabilmiştin","tags":["inferential","second-person","singular"]},{"form":"sığdırabilmişti","tags":["inferential","singular","third-person"]},{"form":"sığdırabilmiştik","tags":["first-person","inferential","plural"]},{"form":"sığdırabilmiştiniz","tags":["inferential","plural","second-person"]},{"form":"sığdırabilmişlerdi","tags":["inferential","plural","third-person"]},{"form":"sığdırabilmişsem","tags":["conditional"]},{"form":"sığdırabilmişsen","tags":["inferential","second-person","singular"]},{"form":"sığdırabilmişse","tags":["inferential","singular","third-person"]},{"form":"sığdırabilmişsek","tags":["first-person","inferential","plural"]},{"form":"sığdırabilmişseniz","tags":["inferential","plural","second-person"]},{"form":"sığdırabilmişlerse","tags":["inferential","plural","third-person"]},{"form":"sığdırabileceğim","tags":["future","singular","third-person"]},{"form":"sığdırabileceksin","tags":["first-person","future","plural"]},{"form":"sığdırabilecek","tags":["future","plural","second-person"]},{"form":"sığdırabileceğiz","tags":["future","plural","third-person"]},{"form":"sığdırabileceksiniz","tags":["future"]},{"form":"sığdırabilecekler","tags":["future"]},{"form":"sığdırabilecekmişim","tags":["future","inferential"]},{"form":"sığdırabilecekmişsin","tags":["future","second-person","singular"]},{"form":"sığdırabilecekmiş","tags":["future","singular","third-person"]},{"form":"sığdırabilecekmişiz","tags":["first-person","future","plural"]},{"form":"sığdırabilecekmişsiniz","tags":["future","plural","second-person"]},{"form":"sığdırabileceklermiş","tags":["future","plural","third-person"]},{"form":"sığdırabilecektim","tags":["future","past"]},{"form":"sığdırabilecektin","tags":["future","second-person","singular"]},{"form":"sığdırabilecekti","tags":["future","singular","third-person"]},{"form":"sığdırabilecektik","tags":["first-person","future","plural"]},{"form":"sığdırabilecektiniz","tags":["future","plural","second-person"]},{"form":"sığdırabileceklerdi","tags":["future","plural","third-person"]},{"form":"sığdırabileceksem","tags":["conditional","future"]},{"form":"sığdırabileceksen","tags":["future","second-person","singular"]},{"form":"sığdırabilecekse","tags":["future","singular","third-person"]},{"form":"sığdırabileceksek","tags":["first-person","future","plural"]},{"form":"sığdırabilecekseniz","tags":["future","plural","second-person"]},{"form":"sığdırabileceklerse","tags":["future","plural","third-person"]},{"form":"sığdırabilmekteyim","tags":["progressive","singular","third-person"]},{"form":"sığdırabilmektesin","tags":["first-person","plural","progressive"]},{"form":"sığdırabilmekte","tags":["plural","progressive","second-person"]},{"form":"sığdırabilmekteyiz","tags":["plural","progressive","third-person"]},{"form":"sığdırabilmektesiniz","tags":["progressive"]},{"form":"sığdırabilmekteler","tags":["progressive"]},{"form":"sığdırabilmekteymişim","tags":["inferential","progressive"]},{"form":"sığdırabilmekteymişsin","tags":["progressive","second-person","singular"]},{"form":"sığdırabilmekteymiş","tags":["progressive","singular","third-person"]},{"form":"sığdırabilmekteymişiz","tags":["first-person","plural","progressive"]},{"form":"sığdırabilmekteymişsiniz","tags":["plural","progressive","second-person"]},{"form":"sığdırabilmektelermiş","tags":["plural","progressive","third-person"]},{"form":"sığdırabilmekteydim","tags":["past","progressive"]},{"form":"sığdırabilmekteydin","tags":["progressive","second-person","singular"]},{"form":"sığdırabilmekteydi","tags":["progressive","singular","third-person"]},{"form":"sığdırabilmekteydik","tags":["first-person","plural","progressive"]},{"form":"sığdırabilmekteydiniz","tags":["plural","progressive","second-person"]},{"form":"sığdırabilmektelerdi","tags":["plural","progressive","third-person"]},{"form":"sığdırabilmekteysem","tags":["conditional","progressive"]},{"form":"sığdırabilmekteysen","tags":["progressive","second-person","singular"]},{"form":"sığdırabilmekteyse","tags":["progressive","singular","third-person"]},{"form":"sığdırabilmekteysek","tags":["first-person","plural","progressive"]},{"form":"sığdırabilmekteyseniz","tags":["plural","progressive","second-person"]},{"form":"sığdırabilmektelerse","tags":["plural","progressive","third-person"]},{"form":"sığdırabilmeliyim","tags":["necessitative","singular","third-person"]},{"form":"sığdırabilmelisin","tags":["first-person","necessitative","plural"]},{"form":"sığdırabilmeli","tags":["necessitative","plural","second-person"]},{"form":"sığdırabilmeliyiz","tags":["necessitative","plural","third-person"]},{"form":"sığdırabilmelisiniz","tags":["necessitative"]},{"form":"sığdırabilmeliler","tags":["necessitative"]},{"form":"sığdırabilmeliymişim","tags":["inferential"]},{"form":"sığdırabilmeliymişsin","tags":["necessitative","second-person","singular"]},{"form":"sığdırabilmeliymiş","tags":["necessitative","singular","third-person"]},{"form":"sığdırabilmeliymişiz","tags":["first-person","necessitative","plural"]},{"form":"sığdırabilmeliymişsiniz","tags":["necessitative","plural","second-person"]},{"form":"sığdırabilmelilermiş","tags":["necessitative","plural","third-person"]},{"form":"sığdırabilmeliydim","tags":["necessitative","past"]},{"form":"sığdırabilmeliydin","tags":["necessitative","second-person","singular"]},{"form":"sığdırabilmeliydi","tags":["necessitative","singular","third-person"]},{"form":"sığdırabilmeliydik","tags":["first-person","necessitative","plural"]},{"form":"sığdırabilmeliydiniz","tags":["necessitative","plural","second-person"]},{"form":"sığdırabilmelilerdi","tags":["necessitative","plural","third-person"]},{"form":"sığdırabilmeliysem","tags":["conditional"]},{"form":"sığdırabilmeliysen","tags":["necessitative","second-person","singular"]},{"form":"sığdırabilmeliyse","tags":["necessitative","singular","third-person"]},{"form":"sığdırabilmeliysek","tags":["first-person","necessitative","plural"]},{"form":"sığdırabilmeliyseniz","tags":["necessitative","plural","second-person"]},{"form":"sığdırabilmelilerse","tags":["necessitative","plural","third-person"]},{"form":"sığdırabildim","tags":["past","singular","third-person"]},{"form":"sığdırabildin","tags":["first-person","past","plural"]},{"form":"sığdırabildi","tags":["past","plural","second-person"]},{"form":"sığdırabildik","tags":["past","plural","third-person"]},{"form":"sığdırabildiniz","tags":["past"]},{"form":"sığdırabildiler","tags":["past"]},{"form":"sığdırabildiysem","tags":["conditional","past"]},{"form":"sığdırabildiysen","tags":["past","second-person","singular"]},{"form":"sığdırabildiyse","tags":["past","singular","third-person"]},{"form":"sığdırabildiysek","tags":["first-person","past","plural"]},{"form":"sığdırabildiyseniz","tags":["past","plural","second-person"]},{"form":"sığdırabildilerse","tags":["past","plural","third-person"]},{"form":"sığdırabilsem","tags":["conditional","singular","third-person"]},{"form":"sığdırabilsen","tags":["conditional","first-person","plural"]},{"form":"sığdırabilse","tags":["conditional","plural","second-person"]},{"form":"sığdırabilsek","tags":["conditional","plural","third-person"]},{"form":"sığdırabilseniz","tags":["conditional"]},{"form":"sığdırabilseler","tags":["conditional"]},{"form":"sığdırabilseymişim","tags":["conditional","past"]},{"form":"sığdırabilseymişsin","tags":["conditional","second-person","singular"]},{"form":"sığdırabilseymiş","tags":["conditional","singular","third-person"]},{"form":"sığdırabilseymişiz","tags":["conditional","first-person","plural"]},{"form":"sığdırabilseymişsiniz","tags":["conditional","plural","second-person"]},{"form":"sığdırabilselermiş","tags":["conditional","plural","third-person"]},{"form":"sığdırabilseydim","tags":["inferential"]},{"form":"sığdırabilseydin","tags":["conditional","second-person","singular"]},{"form":"sığdırabilseydi","tags":["conditional","singular","third-person"]},{"form":"sığdırabilseydik","tags":["conditional","first-person","plural"]},{"form":"sığdırabilseydiniz","tags":["conditional","plural","second-person"]},{"form":"sığdırabilselerdi","tags":["conditional","plural","third-person"]},{"form":"sığdırabileyim","tags":["conditional","optative","singular"]},{"form":"sığdırabilesin","tags":["optative","second-person","singular"]},{"form":"sığdırabile","tags":["optative","singular","third-person"]},{"form":"sığdırabilelim","tags":["first-person","optative","plural"]},{"form":"sığdırabilesiniz","tags":["optative","plural","second-person"]},{"form":"sığdırabileler","tags":["optative","plural","third-person"]},{"form":"-","tags":["imperative","singular","third-person"]},{"form":"sığdırabil","tags":["first-person","imperative","plural"]},{"form":"sığdırabilsin","tags":["imperative","plural","second-person"]},{"form":"-","tags":["imperative","plural","third-person"]},{"form":"sığdırabilin","tags":["imperative"]},{"form":"sığdırabilsinler","tags":["imperative"]},{"form":"sığdırabiliniz","tags":["imperative","second-person","singular"]},{"form":"-","tags":["first-person","imperative","plural"]},{"form":"sığdırabiliniz","tags":["imperative","plural","second-person"]},{"form":"sığdırabilsene","tags":["imperative","second-person","singular"]},{"form":"sığdırabilsenize","tags":["imperative","plural","second-person"]},{"form":"sığdırabilmek","tags":["imperative","infinitive"]},{"form":"sığdırabilme","tags":["imperative","noun-from-verb"]},{"form":"sığdırabilen","tags":["imperative","imperfective","impersonal","participle"]},{"form":"sığdırabilmiş","tags":["imperative","impersonal","participle","perfective"]},{"form":"sığdırabilecek","tags":["imperative","impersonal","participle","prospective"]},{"form":"sığdırabildiğim","tags":["imperative","non-prospective","participle","personal","singular"]},{"form":"sığdırabildiğin","tags":["non-prospective","participle","second-person","singular"]},{"form":"sığdırabildiği","tags":["non-prospective","participle","singular","third-person"]},{"form":"sığdırabildiğimiz","tags":["first-person","non-prospective","participle","plural"]},{"form":"sığdırabildiğiniz","tags":["non-prospective","participle","plural","second-person"]},{"form":"sığdırabildikleri","tags":["non-prospective","participle","plural","third-person"]},{"form":"sığdırabileceğim","tags":["imperative","participle","personal","prospective","singular"]},{"form":"sığdırabileceğin","tags":["participle","prospective","second-person","singular"]},{"form":"sığdırabileceği","tags":["participle","prospective","singular","third-person"]},{"form":"sığdırabileceğimiz","tags":["first-person","participle","plural","prospective"]},{"form":"sığdırabileceğiniz","tags":["participle","plural","prospective","second-person"]},{"form":"sığdırabilecekleri","tags":["participle","plural","prospective","third-person"]},{"form":"sığdırabilirken","tags":["error-unrecognized-form","plural"]},{"form":"sığdırabilince","tags":["error-unrecognized-form","specific"]},{"form":"sığdırabilip","tags":["error-unrecognized-form"]},{"form":"sığdırabileli","tags":["error-unrecognized-form"]},{"form":"sığdırabilesiye","tags":["error-unrecognized-form"]},{"form":"sığdırabildikçe","tags":["error-unrecognized-form"]},{"form":"sığdırabilerek","tags":["error-unrecognized-form","plural"]},{"form":"sığdırabile sığdırabile","tags":["error-unrecognized-form"]},{"form":"sığdırabilircesine","tags":["error-unrecognized-form"]},{"form":"no-table-tags","tags":["table-tags"]},{"form":"tr-conj","tags":["inflection-template"]},{"form":"sığdıramam","tags":["aorist","singular","third-person"]},{"form":"sığdıramazsın","tags":["aorist","first-person","plural"]},{"form":"sığdıramaz","tags":["aorist","plural","second-person"]},{"form":"sığdıramayız","tags":["aorist","plural","third-person"]},{"form":"sığdıramazsınız","tags":["aorist"]},{"form":"sığdıramazlar","tags":["aorist"]},{"form":"sığdıramazmışım","tags":["aorist","inferential"]},{"form":"sığdıramazmışsın","tags":["aorist","second-person","singular"]},{"form":"sığdıramazmış","tags":["aorist","singular","third-person"]},{"form":"sığdıramazmışız","tags":["aorist","first-person","plural"]},{"form":"sığdıramazmışsınız","tags":["aorist","plural","second-person"]},{"form":"sığdıramazlarmış","tags":["aorist","plural","third-person"]},{"form":"sığdıramazdım","tags":["aorist","past"]},{"form":"sığdıramazdın","tags":["aorist","second-person","singular"]},{"form":"sığdıramazdı","tags":["aorist","singular","third-person"]},{"form":"sığdıramazdık","tags":["aorist","first-person","plural"]},{"form":"sığdıramazdınız","tags":["aorist","plural","second-person"]},{"form":"sığdıramazlardı","tags":["aorist","plural","third-person"]},{"form":"sığdıramazsam","tags":["aorist","conditional"]},{"form":"sığdıramazsan","tags":["aorist","second-person","singular"]},{"form":"sığdıramazsa","tags":["aorist","singular","third-person"]},{"form":"sığdıramazsak","tags":["aorist","first-person","plural"]},{"form":"sığdıramazsanız","tags":["aorist","plural","second-person"]},{"form":"sığdıramazlarsa","tags":["aorist","plural","third-person"]},{"form":"sığdıramıyorum","tags":["continuative","singular","third-person"]},{"form":"sığdıramıyorsun","tags":["continuative","first-person","plural"]},{"form":"sığdıramıyor","tags":["continuative","plural","second-person"]},{"form":"sığdıramıyoruz","tags":["continuative","plural","third-person"]},{"form":"sığdıramıyorsunuz","tags":["continuative"]},{"form":"sığdıramıyorlar","tags":["continuative"]},{"form":"sığdıramıyormuşum","tags":["continuative","inferential"]},{"form":"sığdıramıyormuşsun","tags":["continuative","second-person","singular"]},{"form":"sığdıramıyormuş","tags":["continuative","singular","third-person"]},{"form":"sığdıramıyormuşuz","tags":["continuative","first-person","plural"]},{"form":"sığdıramıyormuşsunuz","tags":["continuative","plural","second-person"]},{"form":"sığdıramıyorlarmış","tags":["continuative","plural","third-person"]},{"form":"sığdıramıyordum","tags":["continuative","past"]},{"form":"sığdıramıyordun","tags":["continuative","second-person","singular"]},{"form":"sığdıramıyordu","tags":["continuative","singular","third-person"]},{"form":"sığdıramıyorduk","tags":["continuative","first-person","plural"]},{"form":"sığdıramıyordunuz","tags":["continuative","plural","second-person"]},{"form":"sığdıramıyorlardı","tags":["continuative","plural","third-person"]},{"form":"sığdıramıyorsam","tags":["conditional","continuative"]},{"form":"sığdıramıyorsan","tags":["continuative","second-person","singular"]},{"form":"sığdıramıyorsa","tags":["continuative","singular","third-person"]},{"form":"sığdıramıyorsak","tags":["continuative","first-person","plural"]},{"form":"sığdıramıyorsanız","tags":["continuative","plural","second-person"]},{"form":"sığdıramıyorlarsa","tags":["continuative","plural","third-person"]},{"form":"sığdıramamışım","tags":["inferential","singular","third-person"]},{"form":"sığdıramamışsın","tags":["first-person","inferential","plural"]},{"form":"sığdıramamış","tags":["inferential","plural","second-person"]},{"form":"sığdıramamışız","tags":["inferential","plural","third-person"]},{"form":"sığdıramamışsınız","tags":["inferential"]},{"form":"sığdıramamışlar","tags":["inferential"]},{"form":"sığdıramamışmışım","tags":["inferential"]},{"form":"sığdıramamışmışsın","tags":["inferential","second-person","singular"]},{"form":"sığdıramamışmış","tags":["inferential","singular","third-person"]},{"form":"sığdıramamışmışız","tags":["first-person","inferential","plural"]},{"form":"sığdıramamışmışsınız","tags":["inferential","plural","second-person"]},{"form":"sığdıramamışlarmış","tags":["inferential","plural","third-person"]},{"form":"sığdıramamıştım","tags":["inferential","past"]},{"form":"sığdıramamıştın","tags":["inferential","second-person","singular"]},{"form":"sığdıramamıştı","tags":["inferential","singular","third-person"]},{"form":"sığdıramamıştık","tags":["first-person","inferential","plural"]},{"form":"sığdıramamıştınız","tags":["inferential","plural","second-person"]},{"form":"sığdıramamışlardı","tags":["inferential","plural","third-person"]},{"form":"sığdıramamışsam","tags":["conditional"]},{"form":"sığdıramamışsan","tags":["inferential","second-person","singular"]},{"form":"sığdıramamışsa","tags":["inferential","singular","third-person"]},{"form":"sığdıramamışsak","tags":["first-person","inferential","plural"]},{"form":"sığdıramamışsanız","tags":["inferential","plural","second-person"]},{"form":"sığdıramamışlarsa","tags":["inferential","plural","third-person"]},{"form":"sığdıramayacağım","tags":["future","singular","third-person"]},{"form":"sığdıramayacaksın","tags":["first-person","future","plural"]},{"form":"sığdıramayacak","tags":["future","plural","second-person"]},{"form":"sığdıramayacağız","tags":["future","plural","third-person"]},{"form":"sığdıramayacaksınız","tags":["future"]},{"form":"sığdıramayacaklar","tags":["future"]},{"form":"sığdıramayacakmışım","tags":["future","inferential"]},{"form":"sığdıramayacakmışsın","tags":["future","second-person","singular"]},{"form":"sığdıramayacakmış","tags":["future","singular","third-person"]},{"form":"sığdıramayacakmışız","tags":["first-person","future","plural"]},{"form":"sığdıramayacakmışsınız","tags":["future","plural","second-person"]},{"form":"sığdıramayacaklarmış","tags":["future","plural","third-person"]},{"form":"sığdıramayacaktım","tags":["future","past"]},{"form":"sığdıramayacaktın","tags":["future","second-person","singular"]},{"form":"sığdıramayacaktı","tags":["future","singular","third-person"]},{"form":"sığdıramayacaktık","tags":["first-person","future","plural"]},{"form":"sığdıramayacaktınız","tags":["future","plural","second-person"]},{"form":"sığdıramayacaklardı","tags":["future","plural","third-person"]},{"form":"sığdıramayacaksam","tags":["conditional","future"]},{"form":"sığdıramayacaksan","tags":["future","second-person","singular"]},{"form":"sığdıramayacaksa","tags":["future","singular","third-person"]},{"form":"sığdıramayacaksak","tags":["first-person","future","plural"]},{"form":"sığdıramayacaksanız","tags":["future","plural","second-person"]},{"form":"sığdıramayacaklarsa","tags":["future","plural","third-person"]},{"form":"sığdıramamaktayım","tags":["progressive","singular","third-person"]},{"form":"sığdıramamaktasın","tags":["first-person","plural","progressive"]},{"form":"sığdıramamakta","tags":["plural","progressive","second-person"]},{"form":"sığdıramamaktayız","tags":["plural","progressive","third-person"]},{"form":"sığdıramamaktasınız","tags":["progressive"]},{"form":"sığdıramamaktalar","tags":["progressive"]},{"form":"sığdıramamaktaymışım","tags":["inferential","progressive"]},{"form":"sığdıramamaktaymışsın","tags":["progressive","second-person","singular"]},{"form":"sığdıramamaktaymış","tags":["progressive","singular","third-person"]},{"form":"sığdıramamaktaymışız","tags":["first-person","plural","progressive"]},{"form":"sığdıramamaktaymışsınız","tags":["plural","progressive","second-person"]},{"form":"sığdıramamaktalarmış","tags":["plural","progressive","third-person"]},{"form":"sığdıramamaktaydım","tags":["past","progressive"]},{"form":"sığdıramamaktaydın","tags":["progressive","second-person","singular"]},{"form":"sığdıramamaktaydı","tags":["progressive","singular","third-person"]},{"form":"sığdıramamaktaydık","tags":["first-person","plural","progressive"]},{"form":"sığdıramamaktaydınız","tags":["plural","progressive","second-person"]},{"form":"sığdıramamaktalardı","tags":["plural","progressive","third-person"]},{"form":"sığdıramamaktaysam","tags":["conditional","progressive"]},{"form":"sığdıramamaktaysan","tags":["progressive","second-person","singular"]},{"form":"sığdıramamaktaysa","tags":["progressive","singular","third-person"]},{"form":"sığdıramamaktaysak","tags":["first-person","plural","progressive"]},{"form":"sığdıramamaktaysanız","tags":["plural","progressive","second-person"]},{"form":"sığdıramamaktalarsa","tags":["plural","progressive","third-person"]},{"form":"sığdıramamalıyım","tags":["necessitative","singular","third-person"]},{"form":"sığdıramamalısın","tags":["first-person","necessitative","plural"]},{"form":"sığdıramamalı","tags":["necessitative","plural","second-person"]},{"form":"sığdıramamalıyız","tags":["necessitative","plural","third-person"]},{"form":"sığdıramamalısınız","tags":["necessitative"]},{"form":"sığdıramamalılar","tags":["necessitative"]},{"form":"sığdıramamalıymışım","tags":["inferential"]},{"form":"sığdıramamalıymışsın","tags":["necessitative","second-person","singular"]},{"form":"sığdıramamalıymış","tags":["necessitative","singular","third-person"]},{"form":"sığdıramamalıymışız","tags":["first-person","necessitative","plural"]},{"form":"sığdıramamalıymışsınız","tags":["necessitative","plural","second-person"]},{"form":"sığdıramamalılarmış","tags":["necessitative","plural","third-person"]},{"form":"sığdıramamalıydım","tags":["necessitative","past"]},{"form":"sığdıramamalıydın","tags":["necessitative","second-person","singular"]},{"form":"sığdıramamalıydı","tags":["necessitative","singular","third-person"]},{"form":"sığdıramamalıydık","tags":["first-person","necessitative","plural"]},{"form":"sığdıramamalıydınız","tags":["necessitative","plural","second-person"]},{"form":"sığdıramamalılardı","tags":["necessitative","plural","third-person"]},{"form":"sığdıramamalıysam","tags":["conditional"]},{"form":"sığdıramamalıysan","tags":["necessitative","second-person","singular"]},{"form":"sığdıramamalıysa","tags":["necessitative","singular","third-person"]},{"form":"sığdıramamalıysak","tags":["first-person","necessitative","plural"]},{"form":"sığdıramamalıysanız","tags":["necessitative","plural","second-person"]},{"form":"sığdıramamalılarsa","tags":["necessitative","plural","third-person"]},{"form":"sığdıramadım","tags":["past","singular","third-person"]},{"form":"sığdıramadın","tags":["first-person","past","plural"]},{"form":"sığdıramadı","tags":["past","plural","second-person"]},{"form":"sığdıramadık","tags":["past","plural","third-person"]},{"form":"sığdıramadınız","tags":["past"]},{"form":"sığdıramadılar","tags":["past"]},{"form":"sığdıramadıysam","tags":["conditional","past"]},{"form":"sığdıramadıysan","tags":["past","second-person","singular"]},{"form":"sığdıramadıysa","tags":["past","singular","third-person"]},{"form":"sığdıramadıysak","tags":["first-person","past","plural"]},{"form":"sığdıramadıysanız","tags":["past","plural","second-person"]},{"form":"sığdıramadılarsa","tags":["past","plural","third-person"]},{"form":"sığdıramasam","tags":["conditional","singular","third-person"]},{"form":"sığdıramasan","tags":["conditional","first-person","plural"]},{"form":"sığdıramasa","tags":["conditional","plural","second-person"]},{"form":"sığdıramasak","tags":["conditional","plural","third-person"]},{"form":"sığdıramasanız","tags":["conditional"]},{"form":"sığdıramasalar","tags":["conditional"]},{"form":"sığdıramasaymışım","tags":["inferential"]},{"form":"sığdıramasaymışsın","tags":["conditional","second-person","singular"]},{"form":"sığdıramasaymış","tags":["conditional","singular","third-person"]},{"form":"sığdıramasaymışız","tags":["conditional","first-person","plural"]},{"form":"sığdıramasaymışsınız","tags":["conditional","plural","second-person"]},{"form":"sığdıramasalarmış","tags":["conditional","plural","third-person"]},{"form":"sığdıramasaydım","tags":["conditional","past"]},{"form":"sığdıramasaydın","tags":["conditional","second-person","singular"]},{"form":"sığdıramasaydı","tags":["conditional","singular","third-person"]},{"form":"sığdıramasaydık","tags":["conditional","first-person","plural"]},{"form":"sığdıramasaydınız","tags":["conditional","plural","second-person"]},{"form":"sığdıramasalardı","tags":["conditional","plural","third-person"]},{"form":"sığdıramayayım","tags":["conditional","optative","singular"]},{"form":"sığdıramayasın","tags":["optative","second-person","singular"]},{"form":"sığdıramaya","tags":["optative","singular","third-person"]},{"form":"sığdıramayalım","tags":["first-person","optative","plural"]},{"form":"sığdıramayasınız","tags":["optative","plural","second-person"]},{"form":"sığdıramayalar","tags":["optative","plural","third-person"]},{"form":"-","tags":["imperative","singular","third-person"]},{"form":"sığdırama","tags":["first-person","imperative","plural"]},{"form":"sığdıramasın","tags":["imperative","plural","second-person"]},{"form":"-","tags":["imperative","plural","third-person"]},{"form":"sığdıramayın","tags":["imperative"]},{"form":"sığdıramasınlar","tags":["imperative"]},{"form":"sığdıramayınız","tags":["imperative","second-person","singular"]},{"form":"-","tags":["first-person","imperative","plural"]},{"form":"sığdıramayınız","tags":["imperative","plural","second-person"]},{"form":"sığdıramasana","tags":["imperative","second-person","singular"]},{"form":"sığdıramasanıza","tags":["imperative","plural","second-person"]},{"form":"sığdıramamak","tags":["imperative","infinitive"]},{"form":"sığdıramama","tags":["imperative","noun-from-verb"]},{"form":"sığdıramayan","tags":["imperative","imperfective","impersonal","participle"]},{"form":"sığdıramamış","tags":["imperative","impersonal","participle","perfective"]},{"form":"sığdıramayacak","tags":["imperative","impersonal","participle","prospective"]},{"form":"sığdıramadığım","tags":["imperative","non-prospective","participle","personal","singular"]},{"form":"sığdıramadığın","tags":["non-prospective","participle","second-person","singular"]},{"form":"sığdıramadığı","tags":["non-prospective","participle","singular","third-person"]},{"form":"sığdıramadığımız","tags":["first-person","non-prospective","participle","plural"]},{"form":"sığdıramadığınız","tags":["non-prospective","participle","plural","second-person"]},{"form":"sığdıramadıkları","tags":["non-prospective","participle","plural","third-person"]},{"form":"sığdıramayacağım","tags":["imperative","participle","personal","prospective","singular"]},{"form":"sığdıramayacağın","tags":["participle","prospective","second-person","singular"]},{"form":"sığdıramayacağı","tags":["participle","prospective","singular","third-person"]},{"form":"sığdıramayacağımız","tags":["first-person","participle","plural","prospective"]},{"form":"sığdıramayacağınız","tags":["participle","plural","prospective","second-person"]},{"form":"sığdıramayacakları","tags":["participle","plural","prospective","third-person"]},{"form":"sığdıramazken","tags":["error-unrecognized-form","plural"]},{"form":"sığdıramayınca","tags":["error-unrecognized-form","specific"]},{"form":"sığdıramayıp","tags":["error-unrecognized-form"]},{"form":"sığdıramayalı","tags":["error-unrecognized-form"]},{"form":"sığdıramayasıya","tags":["error-unrecognized-form"]},{"form":"sığdıramadıkça","tags":["error-unrecognized-form"]},{"form":"sığdıramayarak","tags":["error-unrecognized-form","plural"]},{"form":"sığdıramaya sığdıramaya","tags":["error-unrecognized-form"]},{"form":"sığdıramazcasına","tags":["error-unrecognized-form"]}]}