{"word":"ıtır","pos":"noun","senses":[{"glosses":["perfume"],"tags":["dated"]}],"etymology":"Inherited from Ottoman Turkish عطر (ʼıtr, “perfume, scent”), from Arabic عِطْر (ʕiṭr).","forms":[{"form":"ıtırı","tags":["accusative","definite"]},{"form":"ıtırlar","tags":["plural"]},{"form":"no-table-tags","tags":["table-tags"]},{"form":"tr-infl-noun-c","tags":["inflection-template"]},{"form":"ıtır","tags":["nominative","singular"]},{"form":"ıtırlar","tags":["nominative","plural"]},{"form":"ıtırı","tags":["accusative","definite","singular"]},{"form":"ıtırları","tags":["accusative","definite","plural"]},{"form":"ıtıra","tags":["dative","singular"]},{"form":"ıtırlara","tags":["dative","plural"]},{"form":"ıtırda","tags":["locative","singular"]},{"form":"ıtırlarda","tags":["locative","plural"]},{"form":"ıtırdan","tags":["ablative","singular"]},{"form":"ıtırlardan","tags":["ablative","plural"]},{"form":"ıtırın","tags":["genitive","singular"]},{"form":"ıtırların","tags":["genitive","plural"]},{"form":"no-table-tags","tags":["table-tags"]},{"form":"tr-infl-noun-c","tags":["inflection-template"]},{"form":"ıtırım","tags":["first-person","nominative","singular"]},{"form":"ıtırlarım","tags":["first-person","nominative","singular"]},{"form":"ıtırın","tags":["nominative","second-person","singular"]},{"form":"ıtırların","tags":["nominative","second-person","singular"]},{"form":"ıtırı","tags":["nominative","singular","third-person"]},{"form":"ıtırları","tags":["nominative","singular","third-person"]},{"form":"ıtırımız","tags":["first-person","nominative","plural"]},{"form":"ıtırlarımız","tags":["first-person","nominative","plural"]},{"form":"ıtırınız","tags":["nominative","plural","second-person"]},{"form":"ıtırlarınız","tags":["nominative","plural","second-person"]},{"form":"ıtırları","tags":["nominative","plural","third-person"]},{"form":"ıtırımı","tags":["accusative","definite","first-person","singular"]},{"form":"ıtırlarımı","tags":["accusative","definite","first-person","singular"]},{"form":"ıtırını","tags":["accusative","definite","second-person","singular"]},{"form":"ıtırlarını","tags":["accusative","definite","second-person","singular"]},{"form":"ıtırını","tags":["accusative","definite","singular","third-person"]},{"form":"ıtırlarını","tags":["accusative","definite","singular","third-person"]},{"form":"ıtırımızı","tags":["accusative","definite","first-person","plural"]},{"form":"ıtırlarımızı","tags":["accusative","definite","first-person","plural"]},{"form":"ıtırınızı","tags":["accusative","definite","plural","second-person"]},{"form":"ıtırlarınızı","tags":["accusative","definite","plural","second-person"]},{"form":"ıtırlarını","tags":["accusative","definite","plural","third-person"]},{"form":"ıtırıma","tags":["dative","first-person","singular"]},{"form":"ıtırlarıma","tags":["dative","first-person","singular"]},{"form":"ıtırına","tags":["dative","second-person","singular"]},{"form":"ıtırlarına","tags":["dative","second-person","singular"]},{"form":"ıtırına","tags":["dative","singular","third-person"]},{"form":"ıtırlarına","tags":["dative","singular","third-person"]},{"form":"ıtırımıza","tags":["dative","first-person","plural"]},{"form":"ıtırlarımıza","tags":["dative","first-person","plural"]},{"form":"ıtırınıza","tags":["dative","plural","second-person"]},{"form":"ıtırlarınıza","tags":["dative","plural","second-person"]},{"form":"ıtırlarına","tags":["dative","plural","third-person"]},{"form":"ıtırımda","tags":["first-person","locative","singular"]},{"form":"ıtırlarımda","tags":["first-person","locative","singular"]},{"form":"ıtırında","tags":["locative","second-person","singular"]},{"form":"ıtırlarında","tags":["locative","second-person","singular"]},{"form":"ıtırında","tags":["locative","singular","third-person"]},{"form":"ıtırlarında","tags":["locative","singular","third-person"]},{"form":"ıtırımızda","tags":["first-person","locative","plural"]},{"form":"ıtırlarımızda","tags":["first-person","locative","plural"]},{"form":"ıtırınızda","tags":["locative","plural","second-person"]},{"form":"ıtırlarınızda","tags":["locative","plural","second-person"]},{"form":"ıtırlarında","tags":["locative","plural","third-person"]},{"form":"ıtırımdan","tags":["ablative","first-person","singular"]},{"form":"ıtırlarımdan","tags":["ablative","first-person","singular"]},{"form":"ıtırından","tags":["ablative","second-person","singular"]},{"form":"ıtırlarından","tags":["ablative","second-person","singular"]},{"form":"ıtırından","tags":["ablative","singular","third-person"]},{"form":"ıtırlarından","tags":["ablative","singular","third-person"]},{"form":"ıtırımızdan","tags":["ablative","first-person","plural"]},{"form":"ıtırlarımızdan","tags":["ablative","first-person","plural"]},{"form":"ıtırınızdan","tags":["ablative","plural","second-person"]},{"form":"ıtırlarınızdan","tags":["ablative","plural","second-person"]},{"form":"ıtırlarından","tags":["ablative","plural","third-person"]},{"form":"ıtırımın","tags":["first-person","genitive","singular"]},{"form":"ıtırlarımın","tags":["first-person","genitive","singular"]},{"form":"ıtırının","tags":["genitive","second-person","singular"]},{"form":"ıtırlarının","tags":["genitive","second-person","singular"]},{"form":"ıtırının","tags":["genitive","singular","third-person"]},{"form":"ıtırlarının","tags":["genitive","singular","third-person"]},{"form":"ıtırımızın","tags":["first-person","genitive","plural"]},{"form":"ıtırlarımızın","tags":["first-person","genitive","plural"]},{"form":"ıtırınızın","tags":["genitive","plural","second-person"]},{"form":"ıtırlarınızın","tags":["genitive","plural","second-person"]},{"form":"ıtırlarının","tags":["genitive","plural","third-person"]},{"form":"no-table-tags","tags":["table-tags"]},{"form":"tr-infl-noun-c","tags":["inflection-template"]},{"form":"ıtırım","tags":["first-person","singular"]},{"form":"ıtırlarım","tags":["first-person","singular"]},{"form":"ıtırsın","tags":["second-person","singular"]},{"form":"ıtırlarsın","tags":["second-person","singular"]},{"form":"ıtır","tags":["singular","third-person"]},{"form":"ıtırdır","tags":["singular","third-person"]},{"form":"ıtırlar","tags":["singular","third-person"]},{"form":"ıtırlardır","tags":["singular","third-person"]},{"form":"ıtırız","tags":["first-person","plural"]},{"form":"ıtırlarız","tags":["first-person","plural"]},{"form":"ıtırsınız","tags":["plural","second-person"]},{"form":"ıtırlarsınız","tags":["plural","second-person"]},{"form":"ıtırlar","tags":["plural","third-person"]},{"form":"ıtırlardır","tags":["plural","third-person"]}]}